Workbook

Sheet Equity_Home_Bias
A1: Country | E1: Equity Home Bias
A2: Year | B2: 1993 | C2: 1994 | D2: 1995 | E2: 1996 | F2: 1997 | G2: 1998 | H2: 1999 | I2: 2000 | J2: 2001 | K2: 2002 | L2: 2003
A3: Australia | B3: =1-('Portfolio equity assets '!B3)/('Portfolio equity assets '!B3+('Market Cap'!B3/1000000)-'Portfolio equity liabilities '!B3) -> 0.88698561 | C3: =1-('Portfolio equity assets '!C3)/('Portfolio equity assets '!C3+('Market Cap'!C3/1000000)-'Portfolio equity liabilities '!C3) -> 0.88375703 | D3: =1-('Portfolio equity assets '!D3)/('Portfolio equity assets '!D3+('Market Cap'!D3/1000000)-'Portfolio equity liabilities '!D3) -> 0.87706348 | E3: =1-('Portfolio equity assets '!E3)/('Portfolio equity assets '!E3+('Market Cap'!E3/1000000)-'Portfolio equity liabilities '!E3) -> 0.88785598 | F3: =1-('Portfolio equity assets '!F3)/('Portfolio equity assets '!F3+('Market Cap'!F3/1000000)-'Portfolio equity liabilities '!F3) -> 0.87682666 | G3: =1-('Portfolio equity assets '!G3)/('Portfolio equity assets '!G3+('Market Cap'!G3/1000000)-'Portfolio equity liabilities '!G3) -> 0.87433864 | H3: =1-('Portfolio equity assets '!H3)/('Portfolio equity assets '!H3+('Market Cap'!H3/1000000)-'Portfolio equity liabilities '!H3) -> 0.85105262 | I3: =1-('Portfolio equity assets '!I3)/('Portfolio equity assets '!I3+('Market Cap'!I3/1000000)-'Portfolio equity liabilities '!I3) -> 0.82942896 | ... L3: =1-('Portfolio equity assets '!L3)/('Portfolio equity assets '!L3+('Market Cap'!L3/1000000)-'Portfolio equity liabilities '!L3) -> 0.82770469
A4: Austria | B4: =1-('Portfolio equity assets '!B4)/('Portfolio equity assets '!B4+('Market Cap'!B4/1000000)-'Portfolio equity liabilities '!B4) -> 0.86970703 | C4: =1-('Portfolio equity assets '!C4)/('Portfolio equity assets '!C4+('Market Cap'!C4/1000000)-'Portfolio equity liabilities '!C4) -> 0.83437919 | D4: =1-('Portfolio equity assets '!D4)/('Portfolio equity assets '!D4+('Market Cap'!D4/1000000)-'Portfolio equity liabilities '!D4) -> 0.81306708 | E4: =1-('Portfolio equity assets '!E4)/('Portfolio equity assets '!E4+('Market Cap'!E4/1000000)-'Portfolio equity liabilities '!E4) -> 0.79413033 | F4: =1-('Portfolio equity assets '!F4)/('Portfolio equity assets '!F4+('Market Cap'!F4/1000000)-'Portfolio equity liabilities '!F4) -> 0.63560881 | G4: =1-('Portfolio equity assets '!G4)/('Portfolio equity assets '!G4+('Market Cap'!G4/1000000)-'Portfolio equity liabilities '!G4) -> 0.51761387 | H4: =1-('Portfolio equity assets '!H4)/('Portfolio equity assets '!H4+('Market Cap'!H4/1000000)-'Portfolio equity liabilities '!H4) -> 0.38715212 | I4: =1-('Portfolio equity assets '!I4)/('Portfolio equity assets '!I4+('Market Cap'!I4/1000000)-'Portfolio equity liabilities '!I4) -> 0.19534563 | ... L4: =1-('Portfolio equity assets '!L4)/('Portfolio equity assets '!L4+('Market Cap'!L4/1000000)-'Portfolio equity liabilities '!L4) -> 0.39325368
A5: Belgium | B5: =1-('Portfolio equity assets '!B5)/('Portfolio equity assets '!B5+('Market Cap'!B5/1000000)-'Portfolio equity liabilities '!B5) -> 0.54063901 | C5: =1-('Portfolio equity assets '!C5)/('Portfolio equity assets '!C5+('Market Cap'!C5/1000000)-'Portfolio equity liabilities '!C5) -> 0.55426842 | D5: =1-('Portfolio equity assets '!D5)/('Portfolio equity assets '!D5+('Market Cap'!D5/1000000)-'Portfolio equity liabilities '!D5) -> 0.5982306 | E5: =1-('Portfolio equity assets '!E5)/('Portfolio equity assets '!E5+('Market Cap'!E5/1000000)-'Portfolio equity liabilities '!E5) -> 0.6272495 | F5: =1-('Portfolio equity assets '!F5)/('Portfolio equity assets '!F5+('Market Cap'!F5/1000000)-'Portfolio equity liabilities '!F5) -> 0.65882788 | G5: =1-('Portfolio equity assets '!G5)/('Portfolio equity assets '!G5+('Market Cap'!G5/1000000)-'Portfolio equity liabilities '!G5) -> 0.70759472 | H5: =1-('Portfolio equity assets '!H5)/('Portfolio equity assets '!H5+('Market Cap'!H5/1000000)-'Portfolio equity liabilities '!H5) -> 0.57497591 | I5: =1-('Portfolio equity assets '!I5)/('Portfolio equity assets '!I5+('Market Cap'!I5/1000000)-'Portfolio equity liabilities '!I5) -> 0.57434737 | ... L5: =1-('Portfolio equity assets '!L5)/('Portfolio equity assets '!L5+('Market Cap'!L5/1000000)-'Portfolio equity liabilities '!L5) -> 0.4983322
A6: Canada | B6: =1-('Portfolio equity assets '!B6)/('Portfolio equity assets '!B6+('Market Cap'!B6/1000000)-'Portfolio equity liabilities '!B6) -> 0.80380627 | C6: =1-('Portfolio equity assets '!C6)/('Portfolio equity assets '!C6+('Market Cap'!C6/1000000)-'Portfolio equity liabilities '!C6) -> 0.78487726 | D6: =1-('Portfolio equity assets '!D6)/('Portfolio equity assets '!D6+('Market Cap'!D6/1000000)-'Portfolio equity liabilities '!D6) -> 0.77626876 | E6: =1-('Portfolio equity assets '!E6)/('Portfolio equity assets '!E6+('Market Cap'!E6/1000000)-'Portfolio equity liabilities '!E6) -> 0.77578424 | F6: =1-('Portfolio equity assets '!F6)/('Portfolio equity assets '!F6+('Market Cap'!F6/1000000)-'Portfolio equity liabilities '!F6) -> 0.77673219 | G6: =1-('Portfolio equity assets '!G6)/('Portfolio equity assets '!G6+('Market Cap'!G6/1000000)-'Portfolio equity liabilities '!G6) -> 0.74295491 | H6: =1-('Portfolio equity assets '!H6)/('Portfolio equity assets '!H6+('Market Cap'!H6/1000000)-'Portfolio equity liabilities '!H6) -> 0.73578998 | I6: =1-('Portfolio equity assets '!I6)/('Portfolio equity assets '!I6+('Market Cap'!I6/1000000)-'Portfolio equity liabilities '!I6) -> 0.74171494 | ... L6: =1-('Portfolio equity assets '!L6)/('Portfolio equity assets '!L6+('Market Cap'!L6/1000000)-'Portfolio equity liabilities '!L6) -> 0.72340932
A7: Denmark | B7: =1-('Portfolio equity assets '!B7)/('Portfolio equity assets '!B7+('Market Cap'!B7/1000000)-'Portfolio equity liabilities '!B7) -> 0.82856539 | C7: =1-('Portfolio equity assets '!C7)/('Portfolio equity assets '!C7+('Market Cap'!C7/1000000)-'Portfolio equity liabilities '!C7) -> 0.84298177 | D7: =1-('Portfolio equity assets '!D7)/('Portfolio equity assets '!D7+('Market Cap'!D7/1000000)-'Portfolio equity liabilities '!D7) -> 0.81584515 | E7: =1-('Portfolio equity assets '!E7)/('Portfolio equity assets '!E7+('Market Cap'!E7/1000000)-'Portfolio equity liabilities '!E7) -> 0.78578568 | F7: =1-('Portfolio equity assets '!F7)/('Portfolio equity assets '!F7+('Market Cap'!F7/1000000)-'Portfolio equity liabilities '!F7) -> 0.76607176 | G7: =1-('Portfolio equity assets '!G7)/('Portfolio equity assets '!G7+('Market Cap'!G7/1000000)-'Portfolio equity liabilities '!G7) -> 0.70596168 | H7: =1-('Portfolio equity assets '!H7)/('Portfolio equity assets '!H7+('Market Cap'!H7/1000000)-'Portfolio equity liabilities '!H7) -> 0.62778028 | I7: =1-('Portfolio equity assets '!I7)/('Portfolio equity assets '!I7+('Market Cap'!I7/1000000)-'Portfolio equity liabilities '!I7) -> 0.59108755 | ... L7: =1-('Portfolio equity assets '!L7)/('Portfolio equity assets '!L7+('Market Cap'!L7/1000000)-'Portfolio equity liabilities '!L7) -> 0.63419986
A8: Finland | B8: =1-('Portfolio equity assets '!B8)/('Portfolio equity assets '!B8+('Market Cap'!B8/1000000)-'Portfolio equity liabilities '!B8) -> 0.98344512 | C8: =1-('Portfolio equity assets '!C8)/('Portfolio equity assets '!C8+('Market Cap'!C8/1000000)-'Portfolio equity liabilities '!C8) -> 0.98386011 | D8: =1-('Portfolio equity assets '!D8)/('Portfolio equity assets '!D8+('Market Cap'!D8/1000000)-'Portfolio equity liabilities '!D8) -> 0.97560863 | E8: =1-('Portfolio equity assets '!E8)/('Portfolio equity assets '!E8+('Market Cap'!E8/1000000)-'Portfolio equity liabilities '!E8) -> 0.96203556 | F8: =1-('Portfolio equity assets '!F8)/('Portfolio equity assets '!F8+('Market Cap'!F8/1000000)-'Portfolio equity liabilities '!F8) -> 0.93195941 | G8: =1-('Portfolio equity assets '!G8)/('Portfolio equity assets '!G8+('Market Cap'!G8/1000000)-'Portfolio equity liabilities '!G8) -> 0.93417017 | H8: =1-('Portfolio equity assets '!H8)/('Portfolio equity assets '!H8+('Market Cap'!H8/1000000)-'Portfolio equity liabilities '!H8) -> 0.9047727 | I8: =1-('Portfolio equity assets '!I8)/('Portfolio equity assets '!I8+('Market Cap'!I8/1000000)-'Portfolio equity liabilities '!I8) -> 0.81500813 | ... L8: =1-('Portfolio equity assets '!L8)/('Portfolio equity assets '!L8+('Market Cap'!L8/1000000)-'Portfolio equity liabilities '!L8) -> 0.64986035
A9: France | B9: =1-('Portfolio equity assets '!B9)/('Portfolio equity assets '!B9+('Market Cap'!B9/1000000)-'Portfolio equity liabilities '!B9) -> 0.87145567 | C9: =1-('Portfolio equity assets '!C9)/('Portfolio equity assets '!C9+('Market Cap'!C9/1000000)-'Portfolio equity liabilities '!C9) -> 0.86657206 | D9: =1-('Portfolio equity assets '!D9)/('Portfolio equity assets '!D9+('Market Cap'!D9/1000000)-'Portfolio equity liabilities '!D9) -> 0.87302981 | E9: =1-('Portfolio equity assets '!E9)/('Portfolio equity assets '!E9+('Market Cap'!E9/1000000)-'Portfolio equity liabilities '!E9) -> 0.85565347 | F9: =1-('Portfolio equity assets '!F9)/('Portfolio equity assets '!F9+('Market Cap'!F9/1000000)-'Portfolio equity liabilities '!F9) -> 0.82452806 | G9: =1-('Portfolio equity assets '!G9)/('Portfolio equity assets '!G9+('Market Cap'!G9/1000000)-'Portfolio equity liabilities '!G9) -> 0.82849517 | H9: =1-('Portfolio equity assets '!H9)/('Portfolio equity assets '!H9+('Market Cap'!H9/1000000)-'Portfolio equity liabilities '!H9) -> 0.83894798 | I9: =1-('Portfolio equity assets '!I9)/('Portfolio equity assets '!I9+('Market Cap'!I9/1000000)-'Portfolio equity liabilities '!I9) -> 0.81806308 | ... L9: =1-('Portfolio equity assets '!L9)/('Portfolio equity assets '!L9+('Market Cap'!L9/1000000)-'Portfolio equity liabilities '!L9) -> 0.71770474
A10: Germany | B10: =1-('Portfolio equity assets '!B10)/('Portfolio equity assets '!B10+('Market Cap'!B10/1000000)-'Portfolio equity liabilities '!B10) -> 0.7625017 | C10: =1-('Portfolio equity assets '!C10)/('Portfolio equity assets '!C10+('Market Cap'!C10/1000000)-'Portfolio equity liabilities '!C10) -> 0.71790697 | D10: =1-('Portfolio equity assets '!D10)/('Portfolio equity assets '!D10+('Market Cap'!D10/1000000)-'Portfolio equity liabilities '!D10) -> 0.73761951 | E10: =1-('Portfolio equity assets '!E10)/('Portfolio equity assets '!E10+('Market Cap'!E10/1000000)-'Portfolio equity liabilities '!E10) -> 0.73894225 | F10: =1-('Portfolio equity assets '!F10)/('Portfolio equity assets '!F10+('Market Cap'!F10/1000000)-'Portfolio equity liabilities '!F10) -> 0.72558536 | G10: =1-('Portfolio equity assets '!G10)/('Portfolio equity assets '!G10+('Market Cap'!G10/1000000)-'Portfolio equity liabilities '!G10) -> 0.68450085 | H10: =1-('Portfolio equity assets '!H10)/('Portfolio equity assets '!H10+('Market Cap'!H10/1000000)-'Portfolio equity liabilities '!H10) -> 0.67575092 | I10: =1-('Portfolio equity assets '!I10)/('Portfolio equity assets '!I10+('Market Cap'!I10/1000000)-'Portfolio equity liabilities '!I10) -> 0.62849747 | ... L10: =1-('Portfolio equity assets '!L10)/('Portfolio equity assets '!L10+('Market Cap'!L10/1000000)-'Portfolio equity liabilities '!L10) -> 0.55427593
A11: Greece | B11: =1-('Portfolio equity assets '!B11)/('Portfolio equity assets '!B11+('Market Cap'!B11/1000000)-'Portfolio equity liabilities '!B11) -> 0.96521564 | C11: =1-('Portfolio equity assets '!C11)/('Portfolio equity assets '!C11+('Market Cap'!C11/1000000)-'Portfolio equity liabilities '!C11) -> 0.96884882 | D11: =1-('Portfolio equity assets '!D11)/('Portfolio equity assets '!D11+('Market Cap'!D11/1000000)-'Portfolio equity liabilities '!D11) -> 0.96514238 | E11: =1-('Portfolio equity assets '!E11)/('Portfolio equity assets '!E11+('Market Cap'!E11/1000000)-'Portfolio equity liabilities '!E11) -> 0.970909 | F11: =1-('Portfolio equity assets '!F11)/('Portfolio equity assets '!F11+('Market Cap'!F11/1000000)-'Portfolio equity liabilities '!F11) -> 0.96616805 | G11: =1-('Portfolio equity assets '!G11)/('Portfolio equity assets '!G11+('Market Cap'!G11/1000000)-'Portfolio equity liabilities '!G11) -> 0.98298346 | H11: =1-('Portfolio equity assets '!H11)/('Portfolio equity assets '!H11+('Market Cap'!H11/1000000)-'Portfolio equity liabilities '!H11) -> 0.99396657 | I11: =1-('Portfolio equity assets '!I11)/('Portfolio equity assets '!I11+('Market Cap'!I11/1000000)-'Portfolio equity liabilities '!I11) -> 0.98688592 | ... L11: =1-('Portfolio equity assets '!L11)/('Portfolio equity assets '!L11+('Market Cap'!L11/1000000)-'Portfolio equity liabilities '!L11) -> 0.95387176
A12: Iceland | B12: =1-('Portfolio equity assets '!B12)/('Portfolio equity assets '!B12+('Market Cap'!B12/1000000)-'Portfolio equity liabilities '!B12) -> 0.95637397 | C12: =1-('Portfolio equity assets '!C12)/('Portfolio equity assets '!C12+('Market Cap'!C12/1000000)-'Portfolio equity liabilities '!C12) -> 0.91037718 | D12: =1-('Portfolio equity assets '!D12)/('Portfolio equity assets '!D12+('Market Cap'!D12/1000000)-'Portfolio equity liabilities '!D12) -> 0.87535589 | E12: =1-('Portfolio equity assets '!E12)/('Portfolio equity assets '!E12+('Market Cap'!E12/1000000)-'Portfolio equity liabilities '!E12) -> 0.86885512 | F12: =1-('Portfolio equity assets '!F12)/('Portfolio equity assets '!F12+('Market Cap'!F12/1000000)-'Portfolio equity liabilities '!F12) -> 0.82378585 | G12: =1-('Portfolio equity assets '!G12)/('Portfolio equity assets '!G12+('Market Cap'!G12/1000000)-'Portfolio equity liabilities '!G12) -> 0.78877182 | H12: =1-('Portfolio equity assets '!H12)/('Portfolio equity assets '!H12+('Market Cap'!H12/1000000)-'Portfolio equity liabilities '!H12) -> 0.73480056 | I12: =1-('Portfolio equity assets '!I12)/('Portfolio equity assets '!I12+('Market Cap'!I12/1000000)-'Portfolio equity liabilities '!I12) -> 0.68657216 | ... L12: =1-('Portfolio equity assets '!L12)/('Portfolio equity assets '!L12+('Market Cap'!L12/1000000)-'Portfolio equity liabilities '!L12) -> 0.73873673
A13: Ireland | B13: =1-('Portfolio equity assets '!B13)/('Portfolio equity assets '!B13+('Market Cap'!B13/1000000)-'Portfolio equity liabilities '!B13) -> 0.41667125 | C13: =1-('Portfolio equity assets '!C13)/('Portfolio equity assets '!C13+('Market Cap'!C13/1000000)-'Portfolio equity liabilities '!C13) -> 0.25904377 | D13: =1-('Portfolio equity assets '!D13)/('Portfolio equity assets '!D13+('Market Cap'!D13/1000000)-'Portfolio equity liabilities '!D13) -> -0.31170916 | E13: =1-('Portfolio equity assets '!E13)/('Portfolio equity assets '!E13+('Market Cap'!E13/1000000)-'Portfolio equity liabilities '!E13) -> -0.57892401 | F13: =1-('Portfolio equity assets '!F13)/('Portfolio equity assets '!F13+('Market Cap'!F13/1000000)-'Portfolio equity liabilities '!F13) -> -0.53211523 | G13: =1-('Portfolio equity assets '!G13)/('Portfolio equity assets '!G13+('Market Cap'!G13/1000000)-'Portfolio equity liabilities '!G13) -> -2.4355898 | H13: =1-('Portfolio equity assets '!H13)/('Portfolio equity assets '!H13+('Market Cap'!H13/1000000)-'Portfolio equity liabilities '!H13) -> -3.4125001 | I13: =1-('Portfolio equity assets '!I13)/('Portfolio equity assets '!I13+('Market Cap'!I13/1000000)-'Portfolio equity liabilities '!I13) -> 28.720744 | ... L13: =1-('Portfolio equity assets '!L13)/('Portfolio equity assets '!L13+('Market Cap'!L13/1000000)-'Portfolio equity liabilities '!L13) -> 2.2777313
A14: Italy | B14: =1-('Portfolio equity assets '!B14)/('Portfolio equity assets '!B14+('Market Cap'!B14/1000000)-'Portfolio equity liabilities '!B14) -> 0.76336219 | C14: =1-('Portfolio equity assets '!C14)/('Portfolio equity assets '!C14+('Market Cap'!C14/1000000)-'Portfolio equity liabilities '!C14) -> 0.80583048 | D14: =1-('Portfolio equity assets '!D14)/('Portfolio equity assets '!D14+('Market Cap'!D14/1000000)-'Portfolio equity liabilities '!D14) -> 0.78277387 | E14: =1-('Portfolio equity assets '!E14)/('Portfolio equity assets '!E14+('Market Cap'!E14/1000000)-'Portfolio equity liabilities '!E14) -> 0.76036971 | F14: =1-('Portfolio equity assets '!F14)/('Portfolio equity assets '!F14+('Market Cap'!F14/1000000)-'Portfolio equity liabilities '!F14) -> 0.7302817 | G14: =1-('Portfolio equity assets '!G14)/('Portfolio equity assets '!G14+('Market Cap'!G14/1000000)-'Portfolio equity liabilities '!G14) -> 0.76579546 | H14: =1-('Portfolio equity assets '!H14)/('Portfolio equity assets '!H14+('Market Cap'!H14/1000000)-'Portfolio equity liabilities '!H14) -> 0.71437382 | I14: =1-('Portfolio equity assets '!I14)/('Portfolio equity assets '!I14+('Market Cap'!I14/1000000)-'Portfolio equity liabilities '!I14) -> 0.66339972 | ... L14: =1-('Portfolio equity assets '!L14)/('Portfolio equity assets '!L14+('Market Cap'!L14/1000000)-'Portfolio equity liabilities '!L14) -> 0.54297562
... A26: United States | B26: =1-('Portfolio equity assets '!B26)/('Portfolio equity assets '!B26+('Market Cap'!B26/1000000)-'Portfolio equity liabilities '!B26) -> 0.89751099 | C26: =1-('Portfolio equity assets '!C26)/('Portfolio equity assets '!C26+('Market Cap'!C26/1000000)-'Portfolio equity liabilities '!C26) -> 0.881655 | D26: =1-('Portfolio equity assets '!D26)/('Portfolio equity assets '!D26+('Market Cap'!D26/1000000)-'Portfolio equity liabilities '!D26) -> 0.88862576 | E26: =1-('Portfolio equity assets '!E26)/('Portfolio equity assets '!E26+('Market Cap'!E26/1000000)-'Portfolio equity liabilities '!E26) -> 0.88590208 | F26: =1-('Portfolio equity assets '!F26)/('Portfolio equity assets '!F26+('Market Cap'!F26/1000000)-'Portfolio equity liabilities '!F26) -> 0.89555334 | G26: =1-('Portfolio equity assets '!G26)/('Portfolio equity assets '!G26+('Market Cap'!G26/1000000)-'Portfolio equity liabilities '!G26) -> 0.89214801 | H26: =1-('Portfolio equity assets '!H26)/('Portfolio equity assets '!H26+('Market Cap'!H26/1000000)-'Portfolio equity liabilities '!H26) -> 0.8823233 | I26: =1-('Portfolio equity assets '!I26)/('Portfolio equity assets '!I26+('Market Cap'!I26/1000000)-'Portfolio equity liabilities '!I26) -> 0.87900735 | ... L26: =1-('Portfolio equity assets '!L26)/('Portfolio equity assets '!L26+('Market Cap'!L26/1000000)-'Portfolio equity liabilities '!L26) -> 0.85665267

Sheet Debt_Home_Bias
A1: Country | E1: Debt Home Bias
A2: Year | B2: 1993 | C2: 1994 | D2: 1995 | E2: 1996 | F2: 1997 | G2: 1998 | H2: 1999 | I2: 2000 | J2: 2001 | K2: 2002 | L2: 2003
A3: Australia | B3: =1-('Portfolio debt assets '!B3)/(('Portfolio debt assets '!B3+('Domestic debt'!B3*1000))) -> 0.84677142 | C3: =1-('Portfolio debt assets '!C3)/(('Portfolio debt assets '!C3+('Domestic debt'!C3*1000))) -> 0.88904629 | D3: =1-('Portfolio debt assets '!D3)/(('Portfolio debt assets '!D3+('Domestic debt'!D3*1000))) -> 0.86869897 | E3: =1-('Portfolio debt assets '!E3)/(('Portfolio debt assets '!E3+('Domestic debt'!E3*1000))) -> 0.85607606 | F3: =1-('Portfolio debt assets '!F3)/(('Portfolio debt assets '!F3+('Domestic debt'!F3*1000))) -> 0.82038384 | G3: =1-('Portfolio debt assets '!G3)/(('Portfolio debt assets '!G3+('Domestic debt'!G3*1000))) -> 0.81451179 | H3: =1-('Portfolio debt assets '!H3)/(('Portfolio debt assets '!H3+('Domestic debt'!H3*1000))) -> 0.81868658 | I3: =1-('Portfolio debt assets '!I3)/(('Portfolio debt assets '!I3+('Domestic debt'!I3*1000))) -> 0.78716095 | ... L3: =1-('Portfolio debt assets '!L3)/(('Portfolio debt assets '!L3+('Domestic debt'!L3*1000))) -> 0.78289468
A4: Austria | B4: =1-('Portfolio debt assets '!B4)/(('Portfolio debt assets '!B4+('Domestic debt'!B4*1000))) -> 0.52761025 | C4: =1-('Portfolio debt assets '!C4)/(('Portfolio debt assets '!C4+('Domestic debt'!C4*1000))) -> 0.5475047 | D4: =1-('Portfolio debt assets '!D4)/(('Portfolio debt assets '!D4+('Domestic debt'!D4*1000))) -> 0.54811168 | E4: =1-('Portfolio debt assets '!E4)/(('Portfolio debt assets '!E4+('Domestic debt'!E4*1000))) -> 0.54384118 | F4: =1-('Portfolio debt assets '!F4)/(('Portfolio debt assets '!F4+('Domestic debt'!F4*1000))) -> 0.52965784 | G4: =1-('Portfolio debt assets '!G4)/(('Portfolio debt assets '!G4+('Domestic debt'!G4*1000))) -> 0.51769364 | H4: =1-('Portfolio debt assets '!H4)/(('Portfolio debt assets '!H4+('Domestic debt'!H4*1000))) -> 0.47347473 | I4: =1-('Portfolio debt assets '!I4)/(('Portfolio debt assets '!I4+('Domestic debt'!I4*1000))) -> 0.44531854 | ... L4: =1-('Portfolio debt assets '!L4)/(('Portfolio debt assets '!L4+('Domestic debt'!L4*1000))) -> 0.3832282
A5: Belgium | B5: =1-('Portfolio debt assets '!B5)/(('Portfolio debt assets '!B5+('Domestic debt'!B5*1000))) -> 0.48887332 | C5: =1-('Portfolio debt assets '!C5)/(('Portfolio debt assets '!C5+('Domestic debt'!C5*1000))) -> 0.50257451 | D5: =1-('Portfolio debt assets '!D5)/(('Portfolio debt assets '!D5+('Domestic debt'!D5*1000))) -> 0.50118955 | E5: =1-('Portfolio debt assets '!E5)/(('Portfolio debt assets '!E5+('Domestic debt'!E5*1000))) -> 0.49739693 | F5: =1-('Portfolio debt assets '!F5)/(('Portfolio debt assets '!F5+('Domestic debt'!F5*1000))) -> 0.46793343 | G5: =1-('Portfolio debt assets '!G5)/(('Portfolio debt assets '!G5+('Domestic debt'!G5*1000))) -> 0.46765163 | H5: =1-('Portfolio debt assets '!H5)/(('Portfolio debt assets '!H5+('Domestic debt'!H5*1000))) -> 0.41565537 | I5: =1-('Portfolio debt assets '!I5)/(('Portfolio debt assets '!I5+('Domestic debt'!I5*1000))) -> 0.41520566 | ... L5: =1-('Portfolio debt assets '!L5)/(('Portfolio debt assets '!L5+('Domestic debt'!L5*1000))) -> 0.33062987
A6: Canada | B6: =1-('Portfolio debt assets '!B6)/(('Portfolio debt assets '!B6+('Domestic debt'!B6*1000))) -> 0.8433957 | C6: =1-('Portfolio debt assets '!C6)/(('Portfolio debt assets '!C6+('Domestic debt'!C6*1000))) -> 0.81935984 | D6: =1-('Portfolio debt assets '!D6)/(('Portfolio debt assets '!D6+('Domestic debt'!D6*1000))) -> 0.80942379 | E6: =1-('Portfolio debt assets '!E6)/(('Portfolio debt assets '!E6+('Domestic debt'!E6*1000))) -> 0.79597358 | F6: =1-('Portfolio debt assets '!F6)/(('Portfolio debt assets '!F6+('Domestic debt'!F6*1000))) -> 0.78735179 | G6: =1-('Portfolio debt assets '!G6)/(('Portfolio debt assets '!G6+('Domestic debt'!G6*1000))) -> 0.78384481 | H6: =1-('Portfolio debt assets '!H6)/(('Portfolio debt assets '!H6+('Domestic debt'!H6*1000))) -> 0.81432158 | I6: =1-('Portfolio debt assets '!I6)/(('Portfolio debt assets '!I6+('Domestic debt'!I6*1000))) -> 0.81130725 | ... L6: =1-('Portfolio debt assets '!L6)/(('Portfolio debt assets '!L6+('Domestic debt'!L6*1000))) -> 0.80753767
A7: Denmark | B7: =1-('Portfolio debt assets '!B7)/(('Portfolio debt assets '!B7+('Domestic debt'!B7*1000))) -> 0.74807795 | C7: =1-('Portfolio debt assets '!C7)/(('Portfolio debt assets '!C7+('Domestic debt'!C7*1000))) -> 0.77939627 | D7: =1-('Portfolio debt assets '!D7)/(('Portfolio debt assets '!D7+('Domestic debt'!D7*1000))) -> 0.79208074 | E7: =1-('Portfolio debt assets '!E7)/(('Portfolio debt assets '!E7+('Domestic debt'!E7*1000))) -> 0.76214197 | F7: =1-('Portfolio debt assets '!F7)/(('Portfolio debt assets '!F7+('Domestic debt'!F7*1000))) -> 0.74564462 | G7: =1-('Portfolio debt assets '!G7)/(('Portfolio debt assets '!G7+('Domestic debt'!G7*1000))) -> 0.73579459 | H7: =1-('Portfolio debt assets '!H7)/(('Portfolio debt assets '!H7+('Domestic debt'!H7*1000))) -> 0.73744813 | I7: =1-('Portfolio debt assets '!I7)/(('Portfolio debt assets '!I7+('Domestic debt'!I7*1000))) -> 0.71873608 | ... L7: =1-('Portfolio debt assets '!L7)/(('Portfolio debt assets '!L7+('Domestic debt'!L7*1000))) -> 0.70725059
A8: Finland | B8: =1-('Portfolio debt assets '!B8)/(('Portfolio debt assets '!B8+('Domestic debt'!B8*1000))) -> 0.70676897 | C8: =1-('Portfolio debt assets '!C8)/(('Portfolio debt assets '!C8+('Domestic debt'!C8*1000))) -> 0.72024029 | D8: =1-('Portfolio debt assets '!D8)/(('Portfolio debt assets '!D8+('Domestic debt'!D8*1000))) -> 0.71142591 | E8: =1-('Portfolio debt assets '!E8)/(('Portfolio debt assets '!E8+('Domestic debt'!E8*1000))) -> 0.66918801 | F8: =1-('Portfolio debt assets '!F8)/(('Portfolio debt assets '!F8+('Domestic debt'!F8*1000))) -> 0.66740106 | G8: =1-('Portfolio debt assets '!G8)/(('Portfolio debt assets '!G8+('Domestic debt'!G8*1000))) -> 0.67923425 | H8: =1-('Portfolio debt assets '!H8)/(('Portfolio debt assets '!H8+('Domestic debt'!H8*1000))) -> 0.59583787 | I8: =1-('Portfolio debt assets '!I8)/(('Portfolio debt assets '!I8+('Domestic debt'!I8*1000))) -> 0.49173143 | ... L8: =1-('Portfolio debt assets '!L8)/(('Portfolio debt assets '!L8+('Domestic debt'!L8*1000))) -> 0.3317235
A9: France | B9: =1-('Portfolio debt assets '!B9)/(('Portfolio debt assets '!B9+('Domestic debt'!B9*1000))) -> 0.60767544 | C9: =1-('Portfolio debt assets '!C9)/(('Portfolio debt assets '!C9+('Domestic debt'!C9*1000))) -> 0.60072747 | D9: =1-('Portfolio debt assets '!D9)/(('Portfolio debt assets '!D9+('Domestic debt'!D9*1000))) -> 0.59613341 | E9: =1-('Portfolio debt assets '!E9)/(('Portfolio debt assets '!E9+('Domestic debt'!E9*1000))) -> 0.60179655 | F9: =1-('Portfolio debt assets '!F9)/(('Portfolio debt assets '!F9+('Domestic debt'!F9*1000))) -> 0.55627139 | G9: =1-('Portfolio debt assets '!G9)/(('Portfolio debt assets '!G9+('Domestic debt'!G9*1000))) -> 0.54871123 | H9: =1-('Portfolio debt assets '!H9)/(('Portfolio debt assets '!H9+('Domestic debt'!H9*1000))) -> 0.51483255 | I9: =1-('Portfolio debt assets '!I9)/(('Portfolio debt assets '!I9+('Domestic debt'!I9*1000))) -> 0.49878965 | ... L9: =1-('Portfolio debt assets '!L9)/(('Portfolio debt assets '!L9+('Domestic debt'!L9*1000))) -> 0.48026402
A10: Germany | B10: =1-('Portfolio debt assets '!B10)/(('Portfolio debt assets '!B10+('Domestic debt'!B10*1000))) -> 0.59430409 | C10: =1-('Portfolio debt assets '!C10)/(('Portfolio debt assets '!C10+('Domestic debt'!C10*1000))) -> 0.62101167 | D10: =1-('Portfolio debt assets '!D10)/(('Portfolio debt assets '!D10+('Domestic debt'!D10*1000))) -> 0.61983766 | E10: =1-('Portfolio debt assets '!E10)/(('Portfolio debt assets '!E10+('Domestic debt'!E10*1000))) -> 0.61435679 | F10: =1-('Portfolio debt assets '!F10)/(('Portfolio debt assets '!F10+('Domestic debt'!F10*1000))) -> 0.60439397 | G10: =1-('Portfolio debt assets '!G10)/(('Portfolio debt assets '!G10+('Domestic debt'!G10*1000))) -> 0.5908403 | H10: =1-('Portfolio debt assets '!H10)/(('Portfolio debt assets '!H10+('Domestic debt'!H10*1000))) -> 0.5544078 | I10: =1-('Portfolio debt assets '!I10)/(('Portfolio debt assets '!I10+('Domestic debt'!I10*1000))) -> 0.53154689 | ... L10: =1-('Portfolio debt assets '!L10)/(('Portfolio debt assets '!L10+('Domestic debt'!L10*1000))) -> 0.4394564
A11: Greece | B11: =1-('Portfolio debt assets '!B11)/(('Portfolio debt assets '!B11+('Domestic debt'!B11*1000))) -> 0.76131601 | C11: =1-('Portfolio debt assets '!C11)/(('Portfolio debt assets '!C11+('Domestic debt'!C11*1000))) -> 0.73633808 | D11: =1-('Portfolio debt assets '!D11)/(('Portfolio debt assets '!D11+('Domestic debt'!D11*1000))) -> 0.72169652 | E11: =1-('Portfolio debt assets '!E11)/(('Portfolio debt assets '!E11+('Domestic debt'!E11*1000))) -> 0.70952257 | F11: =1-('Portfolio debt assets '!F11)/(('Portfolio debt assets '!F11+('Domestic debt'!F11*1000))) -> 0.70072276 | G11: =1-('Portfolio debt assets '!G11)/(('Portfolio debt assets '!G11+('Domestic debt'!G11*1000))) -> 0.7049645 | H11: =1-('Portfolio debt assets '!H11)/(('Portfolio debt assets '!H11+('Domestic debt'!H11*1000))) -> 0.67118903 | I11: =1-('Portfolio debt assets '!I11)/(('Portfolio debt assets '!I11+('Domestic debt'!I11*1000))) -> 0.69743225 | ... L11: =1-('Portfolio debt assets '!L11)/(('Portfolio debt assets '!L11+('Domestic debt'!L11*1000))) -> 0.58984635
A12: Iceland | B12: =1-('Portfolio debt assets '!B12)/(('Portfolio debt assets '!B12+('Domestic debt'!B12*1000))) -> 0.91590983 | C12: =1-('Portfolio debt assets '!C12)/(('Portfolio debt assets '!C12+('Domestic debt'!C12*1000))) -> 0.90520506 | D12: =1-('Portfolio debt assets '!D12)/(('Portfolio debt assets '!D12+('Domestic debt'!D12*1000))) -> 0.92338241 | E12: =1-('Portfolio debt assets '!E12)/(('Portfolio debt assets '!E12+('Domestic debt'!E12*1000))) -> 0.92365019 | F12: =1-('Portfolio debt assets '!F12)/(('Portfolio debt assets '!F12+('Domestic debt'!F12*1000))) -> 0.91563287 | G12: =1-('Portfolio debt assets '!G12)/(('Portfolio debt assets '!G12+('Domestic debt'!G12*1000))) -> 0.91369232 | H12: =1-('Portfolio debt assets '!H12)/(('Portfolio debt assets '!H12+('Domestic debt'!H12*1000))) -> 0.89855025 | I12: =1-('Portfolio debt assets '!I12)/(('Portfolio debt assets '!I12+('Domestic debt'!I12*1000))) -> 0.9172325 | ... L12: =1-('Portfolio debt assets '!L12)/(('Portfolio debt assets '!L12+('Domestic debt'!L12*1000))) -> 0.79099643
A13: Ireland | B13: =1-('Portfolio debt assets '!B13)/(('Portfolio debt assets '!B13+('Domestic debt'!B13*1000))) -> 0.36512021 | C13: =1-('Portfolio debt assets '!C13)/(('Portfolio debt assets '!C13+('Domestic debt'!C13*1000))) -> 0.3175314 | D13: =1-('Portfolio debt assets '!D13)/(('Portfolio debt assets '!D13+('Domestic debt'!D13*1000))) -> 0.25321904 | E13: =1-('Portfolio debt assets '!E13)/(('Portfolio debt assets '!E13+('Domestic debt'!E13*1000))) -> 0.19717454 | F13: =1-('Portfolio debt assets '!F13)/(('Portfolio debt assets '!F13+('Domestic debt'!F13*1000))) -> 0.13023076 | G13: =1-('Portfolio debt assets '!G13)/(('Portfolio debt assets '!G13+('Domestic debt'!G13*1000))) -> 0.084585143 | H13: =1-('Portfolio debt assets '!H13)/(('Portfolio debt assets '!H13+('Domestic debt'!H13*1000))) -> 0.069728883 | I13: =1-('Portfolio debt assets '!I13)/(('Portfolio debt assets '!I13+('Domestic debt'!I13*1000))) -> 0.062016565 | ... L13: =1-('Portfolio debt assets '!L13)/(('Portfolio debt assets '!L13+('Domestic debt'!L13*1000))) -> 0.099809676
A14: Italy | B14: =1-('Portfolio debt assets '!B14)/(('Portfolio debt assets '!B14+('Domestic debt'!B14*1000))) -> 0.79499056 | C14: =1-('Portfolio debt assets '!C14)/(('Portfolio debt assets '!C14+('Domestic debt'!C14*1000))) -> 0.79831419 | D14: =1-('Portfolio debt assets '!D14)/(('Portfolio debt assets '!D14+('Domestic debt'!D14*1000))) -> 0.78620884 | E14: =1-('Portfolio debt assets '!E14)/(('Portfolio debt assets '!E14+('Domestic debt'!E14*1000))) -> 0.76223226 | F14: =1-('Portfolio debt assets '!F14)/(('Portfolio debt assets '!F14+('Domestic debt'!F14*1000))) -> 0.72349334 | G14: =1-('Portfolio debt assets '!G14)/(('Portfolio debt assets '!G14+('Domestic debt'!G14*1000))) -> 0.68391499 | H14: =1-('Portfolio debt assets '!H14)/(('Portfolio debt assets '!H14+('Domestic debt'!H14*1000))) -> 0.69089243 | I14: =1-('Portfolio debt assets '!I14)/(('Portfolio debt assets '!I14+('Domestic debt'!I14*1000))) -> 0.68015745 | ... L14: =1-('Portfolio debt assets '!L14)/(('Portfolio debt assets '!L14+('Domestic debt'!L14*1000))) -> 0.67951422
... A26: United States | B26: =1-('Portfolio debt assets '!B26)/(('Portfolio debt assets '!B26+('Domestic debt'!B26*1000))) -> 0.87163783 | C26: =1-('Portfolio debt assets '!C26)/(('Portfolio debt assets '!C26+('Domestic debt'!C26*1000))) -> 0.87114703 | D26: =1-('Portfolio debt assets '!D26)/(('Portfolio debt assets '!D26+('Domestic debt'!D26*1000))) -> 0.86202312 | E26: =1-('Portfolio debt assets '!E26)/(('Portfolio debt assets '!E26+('Domestic debt'!E26*1000))) -> 0.85349107 | F26: =1-('Portfolio debt assets '!F26)/(('Portfolio debt assets '!F26+('Domestic debt'!F26*1000))) -> 0.84324624 | G26: =1-('Portfolio debt assets '!G26)/(('Portfolio debt assets '!G26+('Domestic debt'!G26*1000))) -> 0.84598319 | H26: =1-('Portfolio debt assets '!H26)/(('Portfolio debt assets '!H26+('Domestic debt'!H26*1000))) -> 0.8470047 | I26: =1-('Portfolio debt assets '!I26)/(('Portfolio debt assets '!I26+('Domestic debt'!I26*1000))) -> 0.83438266 | ... L26: =1-('Portfolio debt assets '!L26)/(('Portfolio debt assets '!L26+('Domestic debt'!L26*1000))) -> 0.83419044

Sheet Portfolio equity assets 
A1: Country | E1: Portfolio equity assets
A2: Year | B2: 1993 | C2: 1994 | D2: 1995 | E2: 1996 | F2: 1997 | G2: 1998 | H2: 1999 | I2: 2000 | J2: 2001 | K2: 2002 | L2: 2003
A3: Australia | B3: 21523.655 | C3: 22662.363 | D3: 27175.365 | E3: 31681.588 | F3: 33076.226 | G3: 36782.433 | H3: 57208.808 | I3: 59195.454 | J3: 60057.793 | K3: 65500.847 | L3: 92943
A4: Austria | B4: 3722.3091 | C4: 4941.1979 | D4: 5868.3584 | E4: 6454.2633 | F4: 11501.623 | G4: 17225.266 | H4: 28935.795 | I4: 42698.319 | J4: 31190.32 | K4: 30047.485 | L4: 44150.093
A5: Belgium | B5: 59318.748 | C5: 59803.691 | D5: 63766.786 | E5: 64571.161 | F5: 64661.43 | G5: 94141.636 | H5: 125273.62 | I5: 124687 | J5: 110225.95 | K5: 104970.68 | L5: 146643.14
A6: Canada | B6: 69689.522 | C6: 74056.706 | D6: 89141.308 | E6: 117443.82 | F6: 138738.32 | G6: 155873.52 | H6: 235440.45 | I6: 239948.03 | J6: 230766.92 | K6: 203461.21 | L6: 275909.88
A7: Denmark | B7: 7973.4219 | C7: 8877.1988 | D7: 10818.608 | E7: 16149.382 | F7: 22414.298 | G7: 32622.876 | H7: 50132.319 | I7: 56480.145 | J7: 47977.516 | K7: 35795.858 | L7: 52117.83
A8: Finland | B8: 308.23753 | C8: 418.49384 | D8: 737.8516 | E8: 1563.5565 | F8: 3245.3373 | G8: 5270.8006 | H8: 13669.592 | I8: 20263.499 | J8: 20157.094 | K8: 22943.123 | L8: 36081.889
A9: France | B9: 51965.058 | C9: 53744.856 | D9: 58363.265 | E9: 73519.19 | F9: 99126.601 | G9: 143051.53 | H9: 190673.08 | I9: 210060.38 | J9: 201747.2 | K9: 200095.11 | L9: 340240.83
A10: Germany | B10: 115203.61 | C10: 145785.12 | D10: 165971.4 | E10: 187491.64 | F10: 241387.2 | G10: 370572.03 | H10: 507080.89 | I10: 573062.38 | J10: 490736.04 | K10: 437829.1 | L10: 576236.17
A11: Greece | B11: 391.66038 | C11: 411.84906 | D11: 510.77358 | E11: 593.54717 | F11: 999.33962 | G11: 1177 | H11: 1147.2532 | I11: 1345.503 | J11: 2559.2952 | K11: 2596.5812 | L11: 4386.399
A12: Iceland | B12: 22.057001 | C12: 47.58833 | D12: 102.37621 | E12: 182.2694 | F12: 397.28457 | G12: 830.04905 | H12: 1713.122 | I12: 2012.4439 | J12: 1754.4342 | K12: 1848.4239 | L12: 3183.054
A13: Ireland | B13: 13322.184 | C13: 14941.582 | D13: 21132.554 | E13: 26887.85 | F13: 39803.458 | G13: 60785.342 | H13: 118794.95 | I13: 130898.09 | J13: 133758.43 | K13: 152856.41 | L13: 222502.71
... A26: United States | B26: 543862 | C26: 626762 | D26: 790615 | E26: 1006135 | F26: 1207787 | G26: 1474983 | H26: 2003716 | I26: 1852842 | J26: 1612673 | K26: 1373980 | L26: 2079422

Sheet Portfolio debt assets 
A1: Country | E1: Portfolio debt assets
A2: Year | B2: 1993 | C2: 1994 | D2: 1995 | E2: 1996 | F2: 1997 | G2: 1998 | H2: 1999 | I2: 2000 | J2: 2001 | K2: 2002 | L2: 2003
A3: Australia | B3: 26138.768 | C3: 28053.354 | D3: 33098.115 | E3: 41645.804 | F3: 46181.137 | G3: 48065.915 | H3: 56233.992 | I3: 58248.114 | J3: 58008.245 | K3: 72792.371 | L3: 99926.25
A4: Austria | B4: 88487.194 | C4: 99772.085 | D4: 116574.15 | E4: 116578.42 | F4: 117402.2 | G4: 132481.69 | H4: 157599.04 | I4: 174967.13 | J4: 191173.72 | K4: 247000.38 | L4: 327260.91
A5: Belgium | B5: 324619.22 | C5: 380651.75 | D5: 433460.58 | E5: 433144.66 | F5: 425554.63 | G5: 450961.75 | H5: 468771.47 | I5: 436784.14 | J5: 459931.96 | K5: 575445.81 | L5: 768175.55
A6: Canada | B6: 100141.66 | C6: 117441.26 | D6: 136800.22 | E6: 152605.29 | F6: 163079.89 | G6: 160368.16 | H6: 150871.18 | I6: 154029.4 | J6: 159645.59 | K6: 165005.06 | L6: 193738.68
A7: Denmark | B7: 77076.412 | C7: 71181.983 | D7: 75549.946 | E7: 87307.595 | F7: 86580.721 | G7: 101591.64 | H7: 92683.949 | I7: 97502.151 | J7: 97689.715 | K7: 127061.19 | L7: 176731.09
A8: Finland | B8: 25487.078 | C8: 27393.321 | D8: 30987.932 | E8: 38321.885 | F8: 37798.808 | G8: 41238.422 | H8: 50299.317 | I8: 64498.538 | J8: 78155.447 | K8: 100101.11 | L8: 137628.62
A9: France | B9: 661604.61 | C9: 764904.6 | D9: 859826.53 | E9: 834072.94 | F9: 902324.61 | G9: 1016148.8 | H9: 1042245.9 | I9: 1077138.3 | J9: 1206508 | K9: 1521666.6 | L9: 1926305.5
A10: Germany | B10: 943696.92 | C10: 1024490.6 | D10: 1179105.7 | E10: 1185146 | F10: 1140963.7 | G10: 1393041.8 | H10: 1457271.8 | I10: 1512242.1 | J10: 1645212.6 | K10: 2094684.9 | L10: 2699701.7
A11: Greece | B11: 19082.09 | C11: 26281.756 | D11: 33398.12 | E11: 41127.349 | F11: 40491.874 | G11: 42052 | H11: 43991.434 | I11: 37728.984 | J11: 43916.06 | K11: 62865.24 | L11: 91890.702
A12: Iceland | B12: 219.7026 | C12: 318.35508 | D12: 297.13322 | E12: 331.30513 | F12: 408.36797 | G12: 514.71437 | H12: 688.03584 | I12: 588.42975 | J12: 966.61486 | K12: 1625.3413 | L12: 4150.2324
A13: Ireland | B13: 40702.393 | C13: 55200.339 | D13: 83239.762 | E13: 124466.23 | F13: 197007.63 | G13: 335797.65 | H13: 422184.15 | I13: 468654.7 | J13: 561139.57 | K13: 750674.14 | L13: 1057107
... A26: United States | B26: 1321315 | C26: 1410397 | D26: 1634090 | E26: 1875623 | F26: 2157220 | G26: 2278536 | H26: 2419905 | I26: 2726514 | J26: 2873499 | K26: 3250042 | L26: 3321241

Sheet Portfolio equity liabilities 
A1: Country | E1: Portfolio equity liabilities
A2: Year | B2: 1993 | C2: 1994 | D2: 1995 | E2: 1996 | F2: 1997 | G2: 1998 | H2: 1999 | I2: 2000 | J2: 2001 | K2: 2002 | L2: 2003
A3: Australia | B3: 35939.114 | C3: 46570.712 | D3: 51341.675 | E3: 61154.48 | F3: 60327.104 | G3: 73020.337 | H3: 100804.85 | I3: 84947.036 | J3: 89130.336 | K3: 87368.057 | L3: 138978
A4: Austria | B4: 3590.546 | C4: 5378.7948 | D4: 6988.5012 | E4: 9056.0526 | F4: 15661.68 | G4: 15622.806 | H4: 14745.016 | I4: 19569.345 | J4: 14919.797 | K4: 17235.445 | L4: 26470.54
A5: Belgium | B5: 8252.5616 | C5: 9736.9454 | D5: 10011.899 | E5: 11173.254 | F5: 12099.133 | G5: 17842.63 | H5: 15470.84 | I5: 14236.65 | J5: 15663.345 | K5: 18059.663 | L5: 27884.514
A6: Canada | B6: 41005.843 | C6: 44812.446 | D6: 57054.99 | E6: 79913.583 | F6: 84974.68 | G6: 92862.18 | H6: 145243.82 | I6: 152328.56 | J6: 113270.3 | K6: 99394.957 | L6: 172321.6
A7: Denmark | B7: 3248.4312 | C7: 6740.0953 | D7: 8294.2661 | E7: 12448.482 | F7: 20363.317 | G7: 20556.173 | H7: 20740.255 | I7: 26023.315 | J7: 23842.4 | K7: 20671.503 | L7: 31257.85
A8: Finland | B8: 5251.1021 | C8: 12767.33 | D8: 14625.338 | E8: 23456.793 | F8: 28870.257 | G8: 79721.743 | H8: 219531.22 | I8: 204361.06 | J8: 128038.79 | K8: 89172.754 | L8: 103315.11
A9: France | B9: 103818.17 | C9: 102207.26 | D9: 120755.1 | E9: 155317.93 | F9: 208580.35 | G9: 300439.34 | H9: 482208 | I9: 502116.41 | J9: 415991.23 | K9: 345112.49 | L9: 490900.31
A10: Germany | B10: 93608.295 | C10: 99506.069 | D10: 110776.42 | E10: 140288.78 | F10: 186976.17 | G10: 289976.09 | H10: 375408.97 | I10: 300752.49 | J10: 294687.33 | K10: 212677.41 | L10: 362453.21
A11: Greece | B11: 1450.9923 | C11: 2111.8727 | D11: 2917.6321 | E11: 4368.4294 | F11: 5625.004 | G11: 12001 | H11: 15210.649 | I11: 9584.15 | J11: 7711.375 | K11: 8425.2558 | L11: 16139.877
A12: Iceland | B12: 0.46433676 | C12: 0.60383708 | D12: 1.0280769 | E12: 2.4370003 | F12: 1.7292005 | G12: 6.4168631 | H12: 60.372451 | I12: 30.747258 | J12: 117.82419 | K12: 236.41102 | L12: 292.97084
A13: Ireland | B13: 16319.975 | C13: 20612.313 | D13: 30857.853 | E13: 44596.626 | F13: 63195.043 | G13: 109688.5 | H13: 160645.59 | I13: 217502.51 | J13: 279224.92 | K13: 343771.2 | L13: 481711.99
... A26: United States | B26: 373521 | C26: 397720 | D26: 549513 | E26: 672397 | F26: 952893 | G26: 1250342 | H26: 1611534 | I26: 1643205 | J26: 1572681 | K26: 1335792 | L26: 1839509

Sheet Portfolio debt liabilities 
A1: Country | E1: Portfolio debt liabilities
A2: Year | B2: 1993 | C2: 1994 | D2: 1995 | E2: 1996 | F2: 1997 | G2: 1998 | H2: 1999 | I2: 2000 | J2: 2001 | K2: 2002 | L2: 2003
A3: Australia | B3: 147173.48 | C3: 161939.72 | D3: 174379.07 | E3: 204596.58 | F3: 191238.95 | G3: 194006.66 | H3: 222339.6 | I3: 223861.78 | J3: 224252.53 | K3: 270665.59 | L3: 376270.72
A4: Austria | B4: 118857.48 | C4: 137055.98 | D4: 165402.94 | E4: 162097.88 | F4: 163791.96 | G4: 197339.37 | H4: 224503 | I4: 248417.82 | J4: 265346.57 | K4: 319153.43 | L4: 400343.18
A5: Belgium | B5: 335809.14 | C5: 380700.53 | D5: 431282.52 | E5: 407175.97 | F5: 386825.66 | G5: 404457.41 | H5: 419383.29 | I5: 401770.78 | J5: 430202.15 | K5: 541953.55 | L5: 731850.29
A6: Canada | B6: 386955.37 | C6: 387114.01 | D6: 430301.62 | E6: 449359.52 | F6: 475019.64 | G6: 487914.94 | H6: 457978.91 | I6: 433413.93 | J6: 457379.65 | K6: 497447.87 | L6: 552387.18
A7: Denmark | B7: 137565.72 | C7: 127172.18 | D7: 139104.68 | E7: 153339.88 | F7: 155090.44 | G7: 181801.68 | H7: 171396.22 | I7: 166439.14 | J7: 169667.15 | K7: 208159.88 | L7: 270088.86
A8: Finland | B8: 77732.34 | C8: 89099.561 | D8: 88012.777 | E8: 85473.384 | F8: 80344.719 | G8: 89920.888 | H8: 84900.702 | I8: 99527.953 | J8: 108350.97 | K8: 129999.37 | L8: 156084.9
A9: France | B9: 752186.34 | C9: 804545.02 | D9: 925156.23 | E9: 887250.72 | F9: 890987.92 | G9: 991271.64 | H9: 993164.71 | I9: 1091528.4 | J9: 1257677.4 | K9: 1578943.4 | L9: 2109505.9
A10: Germany | B10: 916600.2 | C10: 1053139.6 | D10: 1324221.1 | E10: 1369863 | F10: 1287510 | G10: 1659584 | H10: 1740810.2 | I10: 1864379.9 | J10: 1932322.1 | K10: 2482504.3 | L10: 3043576.8
A11: Greece | B11: 40960.865 | C11: 44380.865 | D11: 50302.865 | E11: 52411.865 | F11: 60011.865 | G11: 66599.792 | H11: 72210.11 | I11: 84761.092 | J11: 98240.849 | K11: 144981.97 | L11: 204482.13
A12: Iceland | B12: 4026.2576 | C12: 4085.5292 | D12: 4264.7719 | E12: 4431.6684 | F12: 4607.3989 | G12: 5838.3524 | H12: 6767.0839 | I12: 8518.4042 | J12: 9061.8747 | K12: 11083.763 | L12: 16041.611
A13: Ireland | B13: 55185.759 | C13: 61251.294 | D13: 95826.262 | E13: 123152.07 | F13: 151112.16 | G13: 228820.68 | H13: 292234.12 | I13: 296082.31 | J13: 348848.01 | K13: 470206.8 | L13: 695414.11
... A26: United States | B26: 2071273.8 | C26: 2269873.6 | D26: 2686887.1 | E26: 3077629.3 | F26: 3577050.7 | G26: 3783522.7 | H26: 3992218.7 | I26: 4511576.6 | J26: 5092559.4 | K26: 5857966 | L26: 6311376.6

Sheet Market Cap
A1: Country | E1: Market cap
A2: Year | B2: 1993 | C2: 1994 | D2: 1995 | E2: 1996 | F2: 1997 | G2: 1998 | H2: 1999 | I2: 2000 | J2: 2001 | K2: 2002 | L2: 2003
A3: Australia | B3: 204866027520 | C3: 218865188864 | D3: 245218329200 | E3: 311980937300 | F3: 295784843900 | G3: 328948659800 | H3: 427683397700 | I3: 372794400000 | J3: 3.7513079e+11 | K3: 3.7884566e+11 | L3: 5.854751e+11
A4: Austria | B4: 28437000192 | C4: 30272000000 | D4: 32513000000 | E4: 33953000000 | F4: 35724000000 | G4: 34106000000 | H4: 3.3024519e+10 | I4: 29935200000 | J4: 2.451162e+10 | K4: 3.1899465e+10 | L4: 5.5085772e+10
A5: Belgium | B5: 78066999296 | C5: 84102995968 | D5: 104960000000 | E5: 119831000000 | F5: 136965000000 | G5: 245657000000 | H5: 184941973500 | I5: 182481000000 | J5: 165843000000 | K5: 127556300000 | L5: 1.7355262e+11
A6: Canada | B6: 326524010496 | C6: 315009007616 | D6: 366344000000 | E6: 486268000000 | F6: 567635000000 | G6: 543394000000 | H6: 800914352600 | I6: 841385200000 | J6: 700751000000 | K6: 575316000000 | L6: 8.9395032e+11
A7: Denmark | B7: 41784999936 | C7: 54399000576 | D7: 56223000000 | E7: 71688000000 | F7: 93766000000 | G7: 98881000000 | H7: 105292683600 | I7: 107666000000 | J7: 8.8370377e+10 | K7: 76787730000 | L7: 1.2161627e+11
A8: Finland | B8: 23562000384 | C8: 38278000640 | D8: 44138000000 | E8: 63078000000 | F8: 73322000000 | G8: 154518000000 | H8: 349408611200 | I8: 293634800000 | J8: 190456000000 | K8: 138832600000 | L8: 1.7028321e+11
A9: France | B9: 456110997504 | C9: 451263004672 | D9: 522053000000 | E9: 591123000000 | F9: 674368000000 | G9: 991484000000 | H9: 1475457198700 | I9: 1446634100000 | J9: 1174428000000 | K9: 966961500000 | L9: 1.3559253e+12
A10: Germany | B10: 463475998720 | C10: 470518988800 | D10: 577365000000 | E10: 670997000000 | F10: 825233000000 | G10: 1093962000000 | H10: 1432190334600 | I10: 1270243200000 | J10: 1.0717487e+12 | K10: 6.9112449e+11 | L10: 1.0790262e+12
A11: Greece | B11: 12318999552 | C11: 14920999936 | D11: 17060000000 | E11: 24178000000 | F11: 34164000000 | G11: 79992000000 | H11: 204212797700 | I11: 110838540000 | J11: 86537760000 | K11: 68740625000 | L11: 1.0684489e+11
A12: Iceland | B12: 483999999 | C12: 484000000 | D12: 720000000 | E12: 1210000000 | F12: 1859000000 | G12: 3106000000 | H12: 4807000000 | I12: 4439060000 | J12: 4.1611492e+09 | K12: 6.3235568e+09 | L12: 9.2932365e+09
A13: Ireland | B13: 25835999998 | C13: 25835999999 | D13: 25836000000 | E13: 34738000000 | F13: 49371000000 | G13: 66596000000 | H13: 68773000000 | I13: 81882400000 | J13: 7.5298234e+10 | K13: 6.0384272e+10 | L13: 8.5070383e+10
... A26: United States | B26: 5136198926336 | C26: 5067015979008 | D26: 6857622000000 | E26: 8484433000000 | F26: 11308779000000 | G26: 13451352000000 | H26: 16635114000000 | I26: 15104037000000 | J26: 13854616194000 | K26: 11098101530000 | L26: 14266265700000
B29: =B3/1000000 -> 204866.03

Sheet Domestic debt
A1: Country | E1: Domestic Debt
A2: Year | B2: 1993 | C2: 1994 | D2: 1995 | E2: 1996 | F2: 1997 | G2: 1998 | H2: 1999 | I2: 2000 | J2: 2001 | K2: 2002 | L2: 2003 | M2: 2004
A3: Australia | B3: 144.448 | C3: 224.785 | D3: 218.98 | E3: 247.714 | F3: 210.929 | G3: 211.066 | H3: 253.914 | I3: 215.424 | J3: 208.615 | K3: 250.741 | L3: 360.34 | M3: 418.556
A4: Austria | B4: 98.831 | C4: 120.721 | D4: 141.397 | E4: 138.987 | F4: 132.208 | G4: 142.202 | H4: 141.72 | I4: 140.47 | J4: 136.382 | K4: 167.09 | L4: 203.342 | M4: 226.421
A5: Belgium | B5: 310.486 | C5: 384.592 | D5: 435.528 | E5: 428.658 | F5: 374.26 | G5: 396.156 | H5: 333.446 | I5: 310.118 | J5: 283.74 | K5: 333.288 | L5: 379.434 | M5: 388.953
A6: Canada | B6: 539.315 | C6: 532.698 | D6: 581.024 | E6: 595.363 | F6: 603.82 | G6: 581.544 | H6: 661.669 | I6: 662.268 | J6: 636.237 | K6: 652.512 | L6: 812.893 | M6: 904.988
A7: Denmark | B7: 228.877 | C7: 251.487 | D7: 287.812 | E7: 279.75 | F7: 253.812 | G7: 282.926 | H7: 260.328 | I7: 249.155 | J7: 262.2 | K7: 341.301 | L7: 426.963 | M7: 527.611
A8: Finland | B8: 61.431 | C8: 70.524 | D8: 76.395 | E8: 77.52 | F8: 75.848 | G8: 87.324 | H8: 74.154 | I8: 62.4 | J8: 55.952 | K8: 63.413 | L8: 68.317 | M8: 76.75
A9: France | B9: 1024.766 | C9: 1150.841 | D9: 1269.16 | E9: 1260.517 | F9: 1131.181 | G9: 1235.511 | H9: 1105.973 | I9: 1071.936 | J9: 1076.914 | K9: 1362.591 | L9: 1780.01 | M9: 2051.949
A10: Germany | B10: 1382.422 | C10: 1678.734 | D10: 1922.479 | E10: 1888.021 | F10: 1743.127 | G10: 2011.599 | H10: 1813.144 | I10: 1715.919 | J10: 1503.237 | K10: 1761.518 | L10: 2116.519 | M10: 2257.627
A11: Greece | B11: 60.865 | C11: 73.398 | D11: 86.608 | E11: 100.458 | F11: 94.807 | G11: 100.48 | H11: 89.798 | I11: 86.967 | J11: 84.951 | K11: 102.846 | L11: 132.149 | M11: 158.046
A12: Iceland | B12: 2.393 | C12: 3.04 | D12: 3.581 | E12: 4.008 | F12: 4.432 | G12: 5.449 | H12: 6.094 | I12: 6.521 | J12: 6.424 | K12: 8.959 | L12: 15.707 | M12: 28.791
A13: Ireland | B13: 23.408 | C13: 25.683 | D13: 28.225 | E13: 30.569 | F13: 29.498 | G13: 31.028 | H13: 31.645 | I13: 30.986 | J13: 28.466 | K13: 38.068 | L13: 117.208 | M13: 187.993
... A26: United States | B26: 8972.333 | C26: 9535.389 | D26: 10209.126 | E26: 10926.484 | F26: 11604.619 | G26: 12515.537 | H26: 13396.953 | I26: 13736.219 | J26: 14577.249 | K26: 15531.253 | L26: 16709.214 | M26: 18976.266
