Workbook

Sheet Table 1
A1: Country | B1: Portfolio equity assets ratio | E1: Debt assets ratio | H1: FDI assets ratio | K1: Portfolio equity liabilities ratio | N1: Debt liabilities ratio | Q1: FDI liabilities ratio
A2: Year | B2: 1993 | C2: 2003 | D2: 2022 | E2: 1993 | F2: 2003 | G2: 2022 | H2: 1993 | I2: 2003 | J2: 2022 | K2: 1993 | L2: 2003 | M2: 2022 | N2: 1993 | O2: 2003 | P2: 2022 | Q2: 1993 | R2: 2003 | S2: 2022
A3: Australia | B3: ='Portfolio equity assets '!B3/GDP!B3 -> 0.069586704 | C3: ='Portfolio equity assets '!L3/GDP!L3 -> 0.17177947 | D3: ='Portfolio equity assets '!AE3/GDP!AE3 -> 0.42617238 | E3: ='Portfolio debt assets '!B3/GDP!B3 -> 0.084507523 | F3: ='Portfolio debt assets '!L3/GDP!L3 -> 0.18468608 | G3: ='Portfolio debt assets '!AE3/GDP!AE3 -> 0.36992396 | H3: ='FDI assets'!B3/GDP!B3 -> 0.14685929 | I3: ='FDI assets'!L3/GDP!L3 -> 0.33998124 | J3: ='FDI assets'!AE3/GDP!AE3 -> 0.41204263 | K3: ='Portfolio equity liabilities '!B3/GDP!B3 -> 0.11619237 | L3: ='Portfolio equity liabilities '!L3/GDP!L3 -> 0.25686246 | M3: ='Portfolio equity liabilities '!AE3/GDP!AE3 -> 0.331863 | N3: ='Portfolio debt liabilities '!B3/GDP!B3 -> 0.47581683 | O3: ='Portfolio debt liabilities '!L3/GDP!L3 -> 0.69543251 | P3: ='Portfolio debt liabilities '!AE3/GDP!AE3 -> 0.79378894 | Q3: ='FDI liabilities'!B3/GDP!B3 -> 0.28335326 | R3: ='FDI liabilities'!L3/GDP!L3 -> 0.39535449 | S3: ='FDI liabilities'!AE3/GDP!AE3 -> 0.48382471
A4: Austria | B4: ='Portfolio equity assets '!B4/GDP!B4 -> 0.019551654 | C4: ='Portfolio equity assets '!L4/GDP!L4 -> 0.16837813 | D4: ='Portfolio equity assets '!AE4/GDP!AE4 -> 0.38441222 | E4: ='Portfolio debt assets '!B4/GDP!B4 -> 0.46478434 | F4: ='Portfolio debt assets '!L4/GDP!L4 -> 1.2480966 | G4: ='Portfolio debt assets '!AE4/GDP!AE4 -> 1.0878561 | H4: ='FDI assets'!B4/GDP!B4 -> 0.042607034 | I4: ='FDI assets'!L4/GDP!L4 -> 0.22232387 | J4: ='FDI assets'!AE4/GDP!AE4 -> 0.69612075 | K4: ='Portfolio equity liabilities '!B4/GDP!B4 -> 0.01885956 | L4: ='Portfolio equity liabilities '!L4/GDP!L4 -> 0.10095245 | M4: ='Portfolio equity liabilities '!AE4/GDP!AE4 -> 0.14328561 | N4: ='Portfolio debt liabilities '!B4/GDP!B4 -> 0.62430611 | O4: ='Portfolio debt liabilities '!L4/GDP!L4 -> 1.5268153 | P4: ='Portfolio debt liabilities '!AE4/GDP!AE4 -> 1.3339526 | Q4: ='FDI liabilities'!B4/GDP!B4 -> 0.059866126 | R4: ='FDI liabilities'!L4/GDP!L4 -> 0.21559119 | S4: ='FDI liabilities'!AE4/GDP!AE4 -> 0.57956433
A5: Belgium | B5: ='Portfolio equity assets '!B5/GDP!B5 -> 0.27120814 | C5: ='Portfolio equity assets '!L5/GDP!L5 -> 0.46113646 | D5: ='Portfolio equity assets '!AE5/GDP!AE5 -> 0.82031602 | E5: ='Portfolio debt assets '!B5/GDP!B5 -> 1.4841745 | F5: ='Portfolio debt assets '!L5/GDP!L5 -> 2.4156176 | G5: ='Portfolio debt assets '!AE5/GDP!AE5 -> 1.5273666 | H5: ='FDI assets'!B5/GDP!B5 -> 0.28640188 | I5: ='FDI assets'!L5/GDP!L5 -> 0.98721339 | J5: ='FDI assets'!AE5/GDP!AE5 -> 1.8459731 | K5: ='Portfolio equity liabilities '!B5/GDP!B5 -> 0.037731105 | L5: ='Portfolio equity liabilities '!L5/GDP!L5 -> 0.087686107 | M5: ='Portfolio equity liabilities '!AE5/GDP!AE5 -> 0.34444723 | N5: ='Portfolio debt liabilities '!B5/GDP!B5 -> 1.5353354 | O5: ='Portfolio debt liabilities '!L5/GDP!L5 -> 2.3013886 | P5: ='Portfolio debt liabilities '!AE5/GDP!AE5 -> 1.7677711 | Q5: ='FDI liabilities'!B5/GDP!B5 -> 0.43112219 | R5: ='FDI liabilities'!L5/GDP!L5 -> 1.1230597 | S5: ='FDI liabilities'!AE5/GDP!AE5 -> 1.5675304
A6: Canada | B6: ='Portfolio equity assets '!B6/GDP!B6 -> 0.1203496 | C6: ='Portfolio equity assets '!L6/GDP!L6 -> 0.30807307 | D6: ='Portfolio equity assets '!AE6/GDP!AE6 -> 0.73556095 | E6: ='Portfolio debt assets '!B6/GDP!B6 -> 0.17293862 | F6: ='Portfolio debt assets '!L6/GDP!L6 -> 0.21632306 | G6: ='Portfolio debt assets '!AE6/GDP!AE6 -> 0.75753627 | H6: ='FDI assets'!B6/GDP!B6 -> 0.26182694 | I6: ='FDI assets'!L6/GDP!L6 -> 0.58902383 | J6: ='FDI assets'!AE6/GDP!AE6 -> 1.0243773 | K6: ='Portfolio equity liabilities '!B6/GDP!B6 -> 0.07081462 | L6: ='Portfolio equity liabilities '!L6/GDP!L6 -> 0.19240937 | M6: ='Portfolio equity liabilities '!AE6/GDP!AE6 -> 0.32872657 | N6: ='Portfolio debt liabilities '!B6/GDP!B6 -> 0.6682486 | O6: ='Portfolio debt liabilities '!L6/GDP!L6 -> 0.6167797 | P6: ='Portfolio debt liabilities '!AE6/GDP!AE6 -> 1.2053797 | Q6: ='FDI liabilities'!B6/GDP!B6 -> 0.32507048 | R6: ='FDI liabilities'!L6/GDP!L6 -> 0.51937748 | S6: ='FDI liabilities'!AE6/GDP!AE6 -> 0.7267139
A7: Denmark | B7: ='Portfolio equity assets '!B7/GDP!B7 -> 0.055682265 | C7: ='Portfolio equity assets '!L7/GDP!L7 -> 0.23896629 | D7: ='Portfolio equity assets '!AE7/GDP!AE7 -> 0.98897005 | E7: ='Portfolio debt assets '!B7/GDP!B7 -> 0.53826189 | F7: ='Portfolio debt assets '!L7/GDP!L7 -> 0.8103325 | G7: ='Portfolio debt assets '!AE7/GDP!AE7 -> 1.0091136 | H7: ='FDI assets'!B7/GDP!B7 -> 0.13714336 | I7: ='FDI assets'!L7/GDP!L7 -> 0.47041229 | J7: ='FDI assets'!AE7/GDP!AE7 -> 0.91159344 | K7: ='Portfolio equity liabilities '!B7/GDP!B7 -> 0.022685367 | L7: ='Portfolio equity liabilities '!L7/GDP!L7 -> 0.14332086 | M7: ='Portfolio equity liabilities '!AE7/GDP!AE7 -> 0.9311431 | N7: ='Portfolio debt liabilities '!B7/GDP!B7 -> 0.96068801 | O7: ='Portfolio debt liabilities '!L7/GDP!L7 -> 1.2383887 | P7: ='Portfolio debt liabilities '!AE7/GDP!AE7 -> 0.99738898 | Q7: ='FDI liabilities'!B7/GDP!B7 -> 0.12889413 | R7: ='FDI liabilities'!L7/GDP!L7 -> 0.45938818 | S7: ='FDI liabilities'!AE7/GDP!AE7 -> 0.59953795
A8: Finland | B8: ='Portfolio equity assets '!B8/GDP!B8 -> 0.00345252 | C8: ='Portfolio equity assets '!L8/GDP!L8 -> 0.21025581 | D8: ='Portfolio equity assets '!AE8/GDP!AE8 -> 0.99195563 | E8: ='Portfolio debt assets '!B8/GDP!B8 -> 0.28547674 | F8: ='Portfolio debt assets '!L8/GDP!L8 -> 0.80198728 | G8: ='Portfolio debt assets '!AE8/GDP!AE8 -> 1.3703348 | H8: ='FDI assets'!B8/GDP!B8 -> 0.14446366 | I8: ='FDI assets'!L8/GDP!L8 -> 0.5426946 | J8: ='FDI assets'!AE8/GDP!AE8 -> 0.7139775 | K8: ='Portfolio equity liabilities '!B8/GDP!B8 -> 0.058816766 | L8: ='Portfolio equity liabilities '!L8/GDP!L8 -> 0.60203613 | M8: ='Portfolio equity liabilities '!AE8/GDP!AE8 -> 0.68621284 | N8: ='Portfolio debt liabilities '!B8/GDP!B8 -> 0.87066769 | O8: ='Portfolio debt liabilities '!L8/GDP!L8 -> 0.90953543 | P8: ='Portfolio debt liabilities '!AE8/GDP!AE8 -> 1.9077037 | Q8: ='FDI liabilities'!B8/GDP!B8 -> 0.088892224 | R8: ='FDI liabilities'!L8/GDP!L8 -> 0.39239361 | S8: ='FDI liabilities'!AE8/GDP!AE8 -> 0.51584631
A9: France | B9: ='Portfolio equity assets '!B9/GDP!B9 -> 0.03924154 | C9: ='Portfolio equity assets '!L9/GDP!L9 -> 0.18450408 | D9: ='Portfolio equity assets '!AE9/GDP!AE9 -> 0.33328173 | E9: ='Portfolio debt assets '!B9/GDP!B9 -> 0.49961233 | F9: ='Portfolio debt assets '!L9/GDP!L9 -> 1.0445873 | G9: ='Portfolio debt assets '!AE9/GDP!AE9 -> 1.8452393 | H9: ='FDI assets'!B9/GDP!B9 -> 0.20601191 | I9: ='FDI assets'!L9/GDP!L9 -> 0.40680151 | J9: ='FDI assets'!AE9/GDP!AE9 -> 0.73547296 | K9: ='Portfolio equity liabilities '!B9/GDP!B9 -> 0.07839854 | L9: ='Portfolio equity liabilities '!L9/GDP!L9 -> 0.26620295 | M9: ='Portfolio equity liabilities '!AE9/GDP!AE9 -> 0.40212118 | N9: ='Portfolio debt liabilities '!B9/GDP!B9 -> 0.56801534 | O9: ='Portfolio debt liabilities '!L9/GDP!L9 -> 1.1439322 | P9: ='Portfolio debt liabilities '!AE9/GDP!AE9 -> 2.281012 | Q9: ='FDI liabilities'!B9/GDP!B9 -> 0.23195312 | R9: ='FDI liabilities'!L9/GDP!L9 -> 0.28981116 | S9: ='FDI liabilities'!AE9/GDP!AE9 -> 0.52217207
A10: Germany | B10: ='Portfolio equity assets '!B10/GDP!B10 -> 0.055587933 | C10: ='Portfolio equity assets '!L10/GDP!L10 -> 0.23040102 | D10: ='Portfolio equity assets '!AE10/GDP!AE10 -> 0.44023919 | E10: ='Portfolio debt assets '!B10/GDP!B10 -> 0.4553517 | F10: ='Portfolio debt assets '!L10/GDP!L10 -> 1.0794428 | G10: ='Portfolio debt assets '!AE10/GDP!AE10 -> 1.4878193 | H10: ='FDI assets'!B10/GDP!B10 -> 0.075611507 | I10: ='FDI assets'!L10/GDP!L10 -> 0.35180388 | J10: ='FDI assets'!AE10/GDP!AE10 -> 0.74194531 | K10: ='Portfolio equity liabilities '!B10/GDP!B10 -> 0.045167781 | L10: ='Portfolio equity liabilities '!L10/GDP!L10 -> 0.14492251 | M10: ='Portfolio equity liabilities '!AE10/GDP!AE10 -> 0.26755293 | N10: ='Portfolio debt liabilities '!B10/GDP!B10 -> 0.44227701 | O10: ='Portfolio debt liabilities '!L10/GDP!L10 -> 1.2169371 | P10: ='Portfolio debt liabilities '!AE10/GDP!AE10 -> 1.2833944 | Q10: ='FDI liabilities'!B10/GDP!B10 -> 0.034340662 | R10: ='FDI liabilities'!L10/GDP!L10 -> 0.33007798 | S10: ='FDI liabilities'!AE10/GDP!AE10 -> 0.49419363
A11: Greece | B11: ='Portfolio equity assets '!B11/GDP!B11 -> 0.0035924894 | C11: ='Portfolio equity assets '!L11/GDP!L11 -> 0.021680501 | D11: ='Portfolio equity assets '!AE11/GDP!AE11 -> 0.05680412 | E11: ='Portfolio debt assets '!B11/GDP!B11 -> 0.17502972 | F11: ='Portfolio debt assets '!L11/GDP!L11 -> 0.45418497 | G11: ='Portfolio debt assets '!AE11/GDP!AE11 -> 1.2709807 | H11: ='FDI assets'!B11/GDP!B11 -> 0.0069441206 | I11: ='FDI assets'!L11/GDP!L11 -> 0.064005234 | J11: ='FDI assets'!AE11/GDP!AE11 -> 0.099193148 | K11: ='Portfolio equity liabilities '!B11/GDP!B11 -> 0.01330917 | L11: ='Portfolio equity liabilities '!L11/GDP!L11 -> 0.079774007 | M11: ='Portfolio equity liabilities '!AE11/GDP!AE11 -> 0.11503369 | N11: ='Portfolio debt liabilities '!B11/GDP!B11 -> 0.37571192 | O11: ='Portfolio debt liabilities '!L11/GDP!L11 -> 1.0106867 | P11: ='Portfolio debt liabilities '!AE11/GDP!AE11 -> 2.6233249 | Q11: ='FDI liabilities'!B11/GDP!B11 -> 0.085668925 | R11: ='FDI liabilities'!L11/GDP!L11 -> 0.11400835 | S11: ='FDI liabilities'!AE11/GDP!AE11 -> 0.25373091
A12: Iceland | B12: ='Portfolio equity assets '!B12/GDP!B12 -> 0.0035432934 | C12: ='Portfolio equity assets '!L12/GDP!L12 -> 0.27850678 | D12: ='Portfolio equity assets '!AE12/GDP!AE12 -> 0.61942112 | E12: ='Portfolio debt assets '!B12/GDP!B12 -> 0.035293591 | F12: ='Portfolio debt assets '!L12/GDP!L12 -> 0.36313172 | G12: ='Portfolio debt assets '!AE12/GDP!AE12 -> 0.22095336 | H12: ='FDI assets'!B12/GDP!B12 -> 0.010169827 | I12: ='FDI assets'!L12/GDP!L12 -> 0.17868977 | J12: ='FDI assets'!AE12/GDP!AE12 -> 0.22254002 | K12: ='Portfolio equity liabilities '!B12/GDP!B12 -> 7.4592251e-05 | L12: ='Portfolio equity liabilities '!L12/GDP!L12 -> 0.025633987 | M12: ='Portfolio equity liabilities '!AE12/GDP!AE12 -> 0.073733066 | N12: ='Portfolio debt liabilities '!B12/GDP!B12 -> 0.64678836 | O12: ='Portfolio debt liabilities '!L12/GDP!L12 -> 1.4035883 | P12: ='Portfolio debt liabilities '!AE12/GDP!AE12 -> 0.58552753 | Q12: ='FDI liabilities'!B12/GDP!B12 -> 0.010643151 | R12: ='FDI liabilities'!L12/GDP!L12 -> 0.13142749 | S12: ='FDI liabilities'!AE12/GDP!AE12 -> 0.3740931
A13: Ireland | B13: ='Portfolio equity assets '!B13/GDP!B13 -> 0.25936813 | C13: ='Portfolio equity assets '!L13/GDP!L13 -> 1.351532 | D13: ='Portfolio equity assets '!AE13/GDP!AE13 -> 3.584759 | E13: ='Portfolio debt assets '!B13/GDP!B13 -> 0.79243036 | F13: ='Portfolio debt assets '!L13/GDP!L13 -> 6.421108 | G13: ='Portfolio debt assets '!AE13/GDP!AE13 -> 8.0367309 | H13: ='FDI assets'!B13/GDP!B13 -> 0.56091531 | I13: ='FDI assets'!L13/GDP!L13 -> 1.1669727 | J13: ='FDI assets'!AE13/GDP!AE13 -> 3.3976299 | K13: ='Portfolio equity liabilities '!B13/GDP!B13 -> 0.31773177 | L13: ='Portfolio equity liabilities '!L13/GDP!L13 -> 2.926028 | M13: ='Portfolio equity liabilities '!AE13/GDP!AE13 -> 8.0204948 | N13: ='Portfolio debt liabilities '!B13/GDP!B13 -> 1.0744054 | O13: ='Portfolio debt liabilities '!L13/GDP!L13 -> 4.2241032 | P13: ='Portfolio debt liabilities '!AE13/GDP!AE13 -> 4.5273259 | Q13: ='FDI liabilities'!B13/GDP!B13 -> 0.65904642 | R13: ='FDI liabilities'!L13/GDP!L13 -> 2.0751697 | S13: ='FDI liabilities'!AE13/GDP!AE13 -> 3.712513
A14: Italy | B14: ='Portfolio equity assets '!B14/GDP!B14 -> 0.028535553 | C14: ='Portfolio equity assets '!L14/GDP!L14 -> 0.21398549 | D14: ='Portfolio equity assets '!AE14/GDP!AE14 -> 0.5535308 | E14: ='Portfolio debt assets '!B14/GDP!B14 -> 0.292633 | F14: ='Portfolio debt assets '!L14/GDP!L14 -> 0.59275625 | G14: ='Portfolio debt assets '!AE14/GDP!AE14 -> 0.65826574 | H14: ='FDI assets'!B14/GDP!B14 -> 0.078170138 | I14: ='FDI assets'!L14/GDP!L14 -> 0.16281696 | J14: ='FDI assets'!AE14/GDP!AE14 -> 0.3728303 | K14: ='Portfolio equity liabilities '!B14/GDP!B14 -> 0.037912697 | L14: ='Portfolio equity liabilities '!L14/GDP!L14 -> 0.13559472 | M14: ='Portfolio equity liabilities '!AE14/GDP!AE14 -> 0.13352181 | N14: ='Portfolio debt liabilities '!B14/GDP!B14 -> 0.44926288 | O14: ='Portfolio debt liabilities '!L14/GDP!L14 -> 0.86503426 | P14: ='Portfolio debt liabilities '!AE14/GDP!AE14 -> 1.2055622 | Q14: ='FDI liabilities'!B14/GDP!B14 -> 0.052059087 | R14: ='FDI liabilities'!L14/GDP!L14 -> 0.15379547 | S14: ='FDI liabilities'!AE14/GDP!AE14 -> 0.32327297
... A26: United States | B26: ='Portfolio equity assets '!B26/GDP!B26 -> 0.079296936 | C26: ='Portfolio equity assets '!L26/GDP!L26 -> 0.18150666 | D26: ='Portfolio equity assets '!AE26/GDP!AE26 -> 0.40474702 | E26: ='Portfolio debt assets '!B26/GDP!B26 -> 0.19265224 | F26: ='Portfolio debt assets '!L26/GDP!L26 -> 0.28990141 | G26: ='Portfolio debt assets '!AE26/GDP!AE26 -> 0.34554868 | H26: ='FDI assets'!B26/GDP!B26 -> 0.1756364 | I26: ='FDI assets'!L26/GDP!L26 -> 0.26511808 | J26: ='FDI assets'!AE26/GDP!AE26 -> 0.36433646 | K26: ='Portfolio equity liabilities '!B26/GDP!B26 -> 0.054460637 | L26: ='Portfolio equity liabilities '!L26/GDP!L26 -> 0.16056536 | M26: ='Portfolio equity liabilities '!AE26/GDP!AE26 -> 0.47340538 | N26: ='Portfolio debt liabilities '!B26/GDP!B26 -> 0.30199879 | O26: ='Portfolio debt liabilities '!L26/GDP!L26 -> 0.55090159 | P26: ='Portfolio debt liabilities '!AE26/GDP!AE26 -> 0.82525999 | Q26: ='FDI liabilities'!B26/GDP!B26 -> 0.13293043 | R26: ='FDI liabilities'!L26/GDP!L26 -> 0.24117951 | S26: ='FDI liabilities'!AE26/GDP!AE26 -> 0.48159539
A28: Average | B28: =AVERAGE(B3:B26) -> 0.080475162 | C28: =AVERAGE(C3:C26) -> 0.29285534 | D28: =AVERAGE(D3:D26) -> 0.72693455 | E28: =AVERAGE(E3:E26) -> 0.44165647 | F28: =AVERAGE(F3:F26) -> 1.1369977 | G28: =AVERAGE(G3:G26) -> 1.3623028 | H28: =AVERAGE(H3:H26) -> 0.15536946 | I28: =AVERAGE(I3:I26) -> 0.5593068 | ... S28: =AVERAGE(S3:S26) -> 0.96556563

Sheet Portfolio equity assets 
A1: Country | K1: Portfolio equity assets
A2: Year | B2: 1993 | C2: 1994 | D2: 1995 | E2: 1996 | F2: 1997 | G2: 1998 | H2: 1999 | I2: 2000 | J2: 2001 | K2: 2002 | L2: 2003 | M2: 2004 | N2: 2005 | O2: 2006 | P2: 2007 | Q2: 2008 | R2: 2009 | S2: 2010 | T2: 2011 | U2: 2012 | V2: 2013 | W2: 2014 | X2: 2015 | Y2: 2016 | Z2: 2017 | AA2: 2018 | AB2: 2019 | AC2: 2020 | AD2: 2021 | AE2: 2022
A3: Australia | B3: 21523.655 | C3: 22662.363 | D3: 27175.365 | E3: 31681.588 | F3: 33076.226 | G3: 36782.433 | H3: 57208.808 | I3: 59195.454 | J3: 60057.793 | K3: 65500.847 | L3: 92943 | M3: 114631.41 | N3: 137520.33 | O3: 188372.13 | P3: 267546.2 | Q3: 161055.22 | R3: 244571.18 | S3: 283837.35 | T3: 299082.01 | U3: 360778.81 | V3: 396083.77 | W3: 420691.24 | X3: 394464.82 | Y3: 427599.84 | Z3: 526353.36 | AA3: 502371.5 | AB3: 620559.25 | AC3: 692134.07 | AD3: 867650.71 | AE3: 725581.5
A4: Austria | B4: 3722.3091 | C4: 4941.1979 | D4: 5868.3584 | E4: 6454.2633 | F4: 11501.623 | G4: 17225.266 | H4: 28935.795 | I4: 42698.319 | J4: 31190.32 | K4: 30047.485 | L4: 44150.093 | M4: 54934.612 | N4: 63610.77 | O4: 88108.617 | P4: 100796.16 | Q4: 54860.814 | R4: 75206.523 | S4: 87505.066 | T4: 74039.546 | U4: 86708.329 | V4: 101631.4 | W4: 99761.383 | X4: 97545.343 | Y4: 106821.44 | Z4: 142346.12 | AA4: 126840.81 | AB4: 158578.02 | AC4: 184369.32 | AD4: 213787.31 | AE4: 181068.15
A5: Belgium | B5: 59318.748 | C5: 59803.691 | D5: 63766.786 | E5: 64571.161 | F5: 64661.43 | G5: 94141.636 | H5: 125273.62 | I5: 124687 | J5: 110225.95 | K5: 104970.68 | L5: 146643.14 | M5: 172163.99 | N5: 204559.98 | O5: 248209.72 | P5: 313728.06 | Q5: 233392.27 | R5: 261133.24 | S5: 260080.64 | T5: 219124.55 | U5: 257308.07 | V5: 312373.05 | W5: 317052.5 | X5: 306907.8 | Y5: 339554.07 | Z5: 430389.19 | AA5: 363493.99 | AB5: 439410.05 | AC5: 513156.04 | AD5: 574769.58 | AE5: 475011.38
A6: Canada | B6: 69689.522 | C6: 74056.706 | D6: 89141.308 | E6: 117443.82 | F6: 138738.32 | G6: 155873.52 | H6: 235440.45 | I6: 239948.03 | J6: 230766.92 | K6: 203461.21 | L6: 275909.88 | M6: 319840.21 | N6: 382600.37 | O6: 499606.16 | P6: 608457.26 | Q6: 359016.78 | R6: 478116.57 | S6: 580362.94 | T6: 584147.26 | U6: 702729.35 | V6: 857015.11 | W6: 934684.26 | X6: 926438.48 | Y6: 1012797.9 | Z6: 1333310.2 | AA6: 1200859.2 | AB6: 1370524.1 | AC6: 1588606.3 | AD6: 2055860.3 | AE6: 1572584.4
A7: Denmark | B7: 7973.4219 | C7: 8877.1988 | D7: 10818.608 | E7: 16149.382 | F7: 22414.298 | G7: 32622.876 | H7: 50132.319 | I7: 56480.145 | J7: 47977.516 | K7: 35795.858 | L7: 52117.83 | M7: 65428.116 | N7: 88374.156 | O7: 132046.84 | P7: 156759.4 | Q7: 85198.774 | R7: 115037.28 | S7: 136051.34 | T7: 129215.57 | U7: 161706.81 | V7: 206434.87 | W7: 216415.69 | X7: 211300.73 | Y7: 231384.56 | Z7: 303430.26 | AA7: 289992.64 | AB7: 345591.76 | AC7: 422701.23 | AD7: 493882.06 | AE7: 396700.61
A8: Finland | B8: 308.23753 | C8: 418.49384 | D8: 737.8516 | E8: 1563.5565 | F8: 3245.3373 | G8: 5270.8006 | H8: 13669.592 | I8: 20263.499 | J8: 20157.094 | K8: 22943.123 | L8: 36081.889 | M8: 53281.593 | N8: 64511.246 | O8: 96258.476 | P8: 122329.98 | Q8: 63345.508 | R8: 103086.09 | S8: 131659.42 | T8: 113492.78 | U8: 139731.86 | V8: 164838.31 | W8: 169793.1 | X8: 169585.71 | Y8: 176148.54 | Z8: 222309.44 | AA8: 208027.04 | AB8: 242316.26 | AC8: 280600.96 | AD8: 320915.41 | AE8: 280846.45
A9: France | B9: 51965.058 | C9: 53744.856 | D9: 58363.265 | E9: 73519.19 | F9: 99126.601 | G9: 143051.53 | H9: 190673.08 | I9: 210060.38 | J9: 201747.2 | K9: 200095.11 | L9: 340240.83 | M9: 442653.9 | N9: 524887.46 | O9: 716800.96 | P9: 826859.43 | Q9: 474750.98 | R9: 646027.6 | S9: 665773.54 | T9: 519334.68 | U9: 652646.49 | V9: 812303.69 | W9: 770696.11 | X9: 748029.44 | Y9: 753755.08 | Z9: 954263.7 | AA9: 786403.52 | AB9: 912445.25 | AC9: 1044512.9 | AD9: 1182670.4 | AE9: 926568.54
A10: Germany | B10: 115203.61 | C10: 145785.12 | D10: 165971.4 | E10: 187491.64 | F10: 241387.2 | G10: 370572.03 | H10: 507080.89 | I10: 573062.38 | J10: 490736.04 | K10: 437829.1 | L10: 576236.17 | M10: 668229.91 | N10: 771379.88 | O10: 884233.8 | P10: 954029.74 | Q10: 589528.3 | R10: 707088.26 | S10: 739717.65 | T10: 647169.96 | U10: 747412.39 | V10: 919610.08 | W10: 939768.03 | X10: 952012.63 | Y10: 1009044.6 | Z10: 1354430.7 | AA10: 1214344.6 | AB10: 1492139.2 | AC10: 1798381.3 | AD10: 2153346.7 | AE10: 1798676.9
A11: Greece | B11: 391.66038 | C11: 411.84906 | D11: 510.77358 | E11: 593.54717 | F11: 999.33962 | G11: 1177 | H11: 1147.2532 | I11: 1345.503 | J11: 2559.2952 | K11: 2596.5812 | L11: 4386.399 | M11: 5649.9908 | N11: 7837.9268 | O11: 12810.459 | P11: 19997.006 | Q11: 15432.561 | R11: 13728.918 | S11: 12246.273 | T11: 11603.695 | U11: 6852.9636 | V11: 7094.0904 | W11: 8155.1097 | X11: 14272.857 | Y11: 11558.207 | Z11: 11402.944 | AA11: 9382.13 | AB11: 10619.5 | AC11: 11993.675 | AD11: 15059.05 | AE11: 12453.622
A12: Iceland | B12: 22.057001 | C12: 47.58833 | D12: 102.37621 | E12: 182.2694 | F12: 397.28457 | G12: 830.04905 | H12: 1713.122 | I12: 2012.4439 | J12: 1754.4342 | K12: 1848.4239 | L12: 3183.054 | M12: 5841.5793 | N12: 9339.4093 | O12: 13392.576 | P12: 20630.703 | Q12: 6706.2863 | R12: 5893.0024 | S12: 4935.4976 | T12: 4678.4125 | U12: 4983.5801 | V12: 5904.6127 | W12: 6051.844 | X12: 6294.0196 | Y12: 7759.883 | Z12: 10150.364 | AA12: 9912.4989 | AB12: 12999.571 | AC12: 16021.877 | AD12: 19863.169 | AE12: 17384.054
A13: Ireland | B13: 13322.184 | C13: 14941.582 | D13: 21132.554 | E13: 26887.85 | F13: 39803.458 | G13: 60785.342 | H13: 118794.95 | I13: 130898.09 | J13: 133758.43 | K13: 152856.41 | L13: 222502.71 | M13: 304942.86 | N13: 383154.76 | O13: 573199.23 | P13: 649172.55 | Q13: 427868.42 | R13: 539873.49 | S13: 603914.3 | T13: 563101.4 | U13: 660459.97 | V13: 848083.06 | W13: 937974.81 | X13: 957468.1 | Y13: 1004338 | Z13: 1330108.9 | AA13: 1253337.6 | AB13: 1563927.8 | AC13: 1913370.4 | AD13: 2324136 | AE13: 1912680.4
... A26: United States | B26: 543862 | C26: 626762 | D26: 790615 | E26: 1006135 | F26: 1207787 | G26: 1474983 | H26: 2003716 | I26: 1852842 | J26: 1612673 | K26: 1373980 | L26: 2079422 | M26: 2560418 | N26: 3317705 | O26: 4328960 | P26: 5247990 | Q26: 2748428 | R26: 3995295 | S26: 4900246 | T26: 4501438 | U26: 5321857 | V26: 6472877 | W26: 6770629 | X26: 6756163 | Y26: 7146320 | Z26: 9118138 | AA26: 7899563 | AB26: 9478014 | AC26: 10615016 | AD26: 12061294 | AE26: 10305962

Sheet Portfolio debt assets 
A1: Country | K1: Portfolio debt assets
A2: Year | B2: 1993 | C2: 1994 | D2: 1995 | E2: 1996 | F2: 1997 | G2: 1998 | H2: 1999 | I2: 2000 | J2: 2001 | K2: 2002 | L2: 2003 | M2: 2004 | N2: 2005 | O2: 2006 | P2: 2007 | Q2: 2008 | R2: 2009 | S2: 2010 | T2: 2011 | U2: 2012 | V2: 2013 | W2: 2014 | X2: 2015 | Y2: 2016 | Z2: 2017 | AA2: 2018 | AB2: 2019 | AC2: 2020 | AD2: 2021 | AE2: 2022
A3: Australia | B3: 26138.768 | C3: 28053.354 | D3: 33098.115 | E3: 41645.804 | F3: 46181.137 | G3: 48065.915 | H3: 56233.992 | I3: 58248.114 | J3: 58008.245 | K3: 72792.371 | L3: 99926.25 | M3: 127040.1 | N3: 157851.89 | O3: 217230.84 | P3: 277487.13 | Q3: 255428.43 | R3: 348938.94 | S3: 427494.4 | T3: 460154.14 | U3: 514079.84 | V3: 512353.56 | W3: 527894.66 | X3: 562039.62 | Y3: 562939.82 | Z3: 597499.5 | AA3: 580068.79 | AB3: 589035.76 | AC3: 640523.74 | AD3: 636264.85 | AE3: 629815.52
A4: Austria | B4: 88487.194 | C4: 99772.085 | D4: 116574.15 | E4: 116578.42 | F4: 117402.2 | G4: 132481.69 | H4: 157599.04 | I4: 174967.13 | J4: 191173.72 | K4: 247000.38 | L4: 327260.91 | M4: 409582.11 | N4: 428661.97 | O4: 575513.2 | P4: 701683.83 | Q4: 694587.73 | R4: 699033.86 | S4: 636132.75 | T4: 635403.24 | U4: 641996.29 | V4: 655497.26 | W4: 576676.86 | X4: 495064.55 | Y4: 464116.01 | Z4: 522925.98 | AA4: 499839.45 | AB4: 520661.07 | AC4: 571165.97 | AD4: 542522.2 | AE4: 512408.51
A5: Belgium | B5: 324619.22 | C5: 380651.75 | D5: 433460.58 | E5: 433144.66 | F5: 425554.63 | G5: 450961.75 | H5: 468771.47 | I5: 436784.14 | J5: 459931.96 | K5: 575445.81 | L5: 768175.55 | M5: 943412.25 | N5: 959219.97 | O5: 1138815.2 | P5: 1479354.5 | Q5: 1400217.2 | R5: 1366985.3 | S5: 1225052.2 | T5: 1229933.5 | U5: 1158856.7 | V5: 1066158.8 | W5: 983476.85 | X5: 880277.09 | Y5: 899150.46 | Z5: 948834.59 | AA5: 853568.88 | AB5: 886542.34 | AC5: 984818.92 | AD5: 936878.79 | AE5: 884435.39
A6: Canada | B6: 100141.66 | C6: 117441.26 | D6: 136800.22 | E6: 152605.29 | F6: 163079.89 | G6: 160368.16 | H6: 150871.18 | I6: 154029.4 | J6: 159645.59 | K6: 165005.06 | L6: 193738.68 | M6: 227670.36 | N6: 272482.53 | O6: 352961.73 | P6: 448896.77 | Q6: 431263.49 | R6: 502999.98 | S6: 563581.24 | T6: 602639.26 | U6: 667458.87 | V6: 669767.2 | W6: 733082.76 | X6: 768649.78 | Y6: 856410.86 | Z6: 940679.26 | AA6: 1018184 | AB6: 1287955.8 | AC6: 1410389.8 | AD6: 1468070.6 | AE6: 1619566.3
A7: Denmark | B7: 77076.412 | C7: 71181.983 | D7: 75549.946 | E7: 87307.595 | F7: 86580.721 | G7: 101591.64 | H7: 92683.949 | I7: 97502.151 | J7: 97689.715 | K7: 127061.19 | L7: 176731.09 | M7: 220596.33 | N7: 232955.36 | O7: 280065.18 | P7: 369626.43 | Q7: 372857.95 | R7: 364452.13 | S7: 381430.53 | T7: 360886.24 | U7: 386395.36 | V7: 415542.89 | W7: 397260.76 | X7: 346554.32 | Y7: 368323.22 | Z7: 430470.38 | AA7: 373999.91 | AB7: 411131.98 | AC7: 491106.05 | AD7: 463041.52 | AE7: 404780.7
A8: Finland | B8: 25487.078 | C8: 27393.321 | D8: 30987.932 | E8: 38321.885 | F8: 37798.808 | G8: 41238.422 | H8: 50299.317 | I8: 64498.538 | J8: 78155.447 | K8: 100101.11 | L8: 137628.62 | M8: 179332.52 | N8: 170366.71 | O8: 221463.4 | P8: 263065.55 | Q8: 258443.24 | R8: 305137.58 | S8: 339007.38 | T8: 407586.03 | U8: 436804.42 | V8: 413356.26 | W8: 379844.54 | X8: 345345.44 | Y8: 307568.46 | Z8: 305190.67 | AA8: 397979.1 | AB8: 401951.4 | AC8: 426375.53 | AD8: 377410.64 | AE8: 387974.68
A9: France | B9: 661604.61 | C9: 764904.6 | D9: 859826.53 | E9: 834072.94 | F9: 902324.61 | G9: 1016148.8 | H9: 1042245.9 | I9: 1077138.3 | J9: 1206508 | K9: 1521666.6 | L9: 1926305.5 | M9: 2389202.9 | N9: 2589121.2 | O9: 3240223.3 | P9: 4157506.6 | Q9: 3977795.2 | R9: 4229386.1 | S9: 4200082.9 | T9: 4007022.5 | U9: 4098596 | V9: 4233474.3 | W9: 4060829.4 | X9: 3697489.8 | Y9: 3691708.8 | Z9: 4210994.4 | AA9: 4416991.3 | AB9: 4703592.6 | AC9: 5533484.7 | AD9: 5366136.8 | AE9: 5130016.3
A10: Germany | B10: 943696.92 | C10: 1024490.6 | D10: 1179105.7 | E10: 1185146 | F10: 1140963.7 | G10: 1393041.8 | H10: 1457271.8 | I10: 1512242.1 | J10: 1645212.6 | K10: 2094684.9 | L10: 2699701.7 | M10: 3212139.6 | N10: 3145739.7 | O10: 4013889.4 | P10: 5040788.4 | Q10: 4909145.2 | R10: 5060879.7 | S10: 5100371.6 | T10: 5094966.7 | U10: 5448611.4 | V10: 5502871 | W10: 5213522.7 | X10: 4784533.8 | Y10: 4898735.8 | Z10: 5725828.8 | AA10: 5681178.6 | AB10: 5792206.6 | AC10: 6790355.4 | AD10: 6673967.8 | AE10: 6078755
A11: Greece | B11: 19082.09 | C11: 26281.756 | D11: 33398.12 | E11: 41127.349 | F11: 40491.874 | G11: 42052 | H11: 43991.434 | I11: 37728.984 | J11: 43916.06 | K11: 62865.24 | L11: 91890.702 | M11: 117944.63 | N11: 130944.95 | O11: 161107.63 | P11: 228234.62 | Q11: 260456.5 | R11: 304147.55 | S11: 245937.02 | T11: 233385.8 | U11: 281337.04 | V11: 258422.4 | W11: 225626.25 | X11: 213715.43 | Y11: 199731.36 | Z11: 190794.59 | AA11: 180693.08 | AB11: 210626.22 | AC11: 272803.48 | AD11: 290163.11 | AE11: 278647.26
A12: Iceland | B12: 219.7026 | C12: 318.35508 | D12: 297.13322 | E12: 331.30513 | F12: 408.36797 | G12: 514.71437 | H12: 688.03584 | I12: 588.42975 | J12: 966.61486 | K12: 1625.3413 | L12: 4150.2324 | M12: 8432.8145 | N12: 19573.134 | O12: 36387.176 | P12: 60770.897 | Q12: 16696.384 | R12: 13847.638 | S12: 14345.215 | T12: 12163.45 | U12: 16972.021 | V12: 18314.409 | W12: 14529.669 | X12: 10306.822 | Y12: 5749.805 | Z12: 5828.6344 | AA12: 6426.124 | AB12: 5583.8398 | AC12: 5928.2761 | AD12: 5952.3393 | AE12: 6201.056
A13: Ireland | B13: 40702.393 | C13: 55200.339 | D13: 83239.762 | E13: 124466.23 | F13: 197007.63 | G13: 335797.65 | H13: 422184.15 | I13: 468654.7 | J13: 561139.57 | K13: 750674.14 | L13: 1057107 | M13: 1333807.8 | N13: 1484361.1 | O13: 1942848.9 | P13: 2503780.1 | Q13: 2390569 | R13: 2433743.9 | S13: 2325995.5 | T13: 2496352.3 | U13: 2551529.6 | V13: 2629499.6 | W13: 2626888.7 | X13: 2670648.6 | Y13: 2687101.2 | Z13: 3246054.2 | AA13: 3235685.3 | AB13: 3797071.8 | AC13: 4455046.7 | AD13: 4715624.3 | AE13: 4288070.1
... A26: United States | B26: 1321315 | C26: 1410397 | D26: 1634090 | E26: 1875623 | F26: 2157220 | G26: 2278536 | H26: 2419905 | I26: 2726514 | J26: 2873499 | K26: 3250042 | L26: 3321241 | M26: 4092756 | N26: 4614054 | O26: 5692811 | P26: 6762711 | Q26: 6547273 | R26: 6592975 | S26: 7240924 | T26: 7239763 | U26: 7027158 | V26: 7010835 | W26: 7107799 | X26: 6661504 | Y26: 6726621 | Z26: 7559472 | AA26: 7891171 | AB26: 8393516 | AC26: 8885433 | AD26: 9339840 | AE26: 8798611

Sheet FDI assets
A1: Country | K1: Portfolio FDI assets
A2: Year | B2: 1993 | C2: 1994 | D2: 1995 | E2: 1996 | F2: 1997 | G2: 1998 | H2: 1999 | I2: 2000 | J2: 2001 | K2: 2002 | L2: 2003 | M2: 2004 | N2: 2005 | O2: 2006 | P2: 2007 | Q2: 2008 | R2: 2009 | S2: 2010 | T2: 2011 | U2: 2012 | V2: 2013 | W2: 2014 | X2: 2015 | Y2: 2016 | Z2: 2017 | AA2: 2018 | AB2: 2019 | AC2: 2020 | AD2: 2021 | AE2: 2022
A3: Australia | B3: 45424.608 | C3: 53794.175 | D3: 60484.315 | E3: 73383.943 | F3: 77802.494 | G3: 86399.06 | H3: 99103.658 | I3: 95978.284 | J3: 122263.68 | K3: 128911.85 | L3: 183950.25 | M3: 229203.61 | N3: 229154.32 | O3: 294751.34 | P3: 377417.37 | Q3: 275773.2 | R3: 396182.26 | S3: 483198.82 | T3: 458559.65 | U3: 515197.33 | V3: 490024.4 | W3: 502780.96 | X3: 466336.14 | Y3: 479705.55 | Z3: 552420.96 | AA3: 536127.09 | AB3: 617473.11 | AC3: 647903.79 | AD3: 670336.13 | AE3: 701524.83
A4: Austria | B4: 8111.6693 | C4: 9390.0994 | D4: 11706.979 | E4: 11867.811 | F4: 15158.711 | G4: 18725.811 | H4: 20457.674 | I4: 26261.501 | J4: 29934.054 | K4: 44075.754 | L4: 58295.1 | M4: 73276.328 | N4: 146925.03 | O4: 212268.79 | P4: 305613.85 | Q4: 304464.99 | R4: 339098.51 | S4: 318054.35 | T4: 337370.19 | U4: 366199.47 | V4: 393221.4 | W4: 366567.14 | X4: 329136.87 | Y4: 292924.9 | Z4: 361317.91 | AA4: 320595.42 | AB4: 314153.19 | AC4: 326438.05 | AD4: 327388.22 | AE4: 327890.97
A5: Belgium | B5: 62641.927 | C5: 69540.636 | D5: 80690.022 | E5: 87310.795 | F5: 94733.911 | G5: 134982.26 | H5: 151795.06 | I5: 179772.6 | J5: 181458.79 | K5: 223940.45 | L5: 313937.59 | M5: 369229.9 | N5: 378157.55 | O5: 481355.6 | P5: 621095.18 | Q5: 907192.17 | R5: 1046454.7 | S5: 1076031.2 | T5: 1130235.9 | U5: 1187464 | V5: 1222021.9 | W5: 1131255.9 | X5: 1076346.5 | Y5: 1087541.3 | Z5: 1200765.5 | AA5: 1020819 | AB5: 1068524.2 | AC5: 1101998.4 | AD5: 1126559.8 | AE5: 1068927.3
A6: Canada | B6: 151613.25 | C6: 157393.14 | D6: 204696.5 | E6: 256724.85 | F6: 319745.44 | G6: 375502.92 | H6: 426324.23 | I6: 464889.28 | J6: 423722.42 | K6: 400657.5 | L6: 527529.06 | M6: 661000.8 | N6: 722843.47 | O6: 815522.84 | P6: 986214.95 | Q6: 687769.14 | R6: 931883.32 | S6: 1051858.3 | T6: 931919.76 | U6: 1023243.5 | V6: 1205039.1 | W6: 1214407.6 | X6: 1213977.3 | Y6: 1349216.1 | Z6: 1594928.9 | AA6: 1439622.3 | AB6: 1776032.5 | AC6: 1954376 | AD6: 2253072.1 | AE6: 2190056.3
A7: Denmark | B7: 19638.243 | C7: 25480.848 | D7: 31013.343 | E7: 31962.318 | F7: 31936.713 | G7: 39272.528 | H7: 50851.084 | I7: 72869.771 | J7: 78251.62 | K7: 86678.574 | L7: 102595.51 | M7: 126216.26 | N7: 127839.53 | O7: 145874.7 | P7: 179063.5 | Q7: 194003.67 | R7: 213393.19 | S7: 221647.87 | T7: 234019.08 | U7: 245190.4 | V7: 260865.19 | W7: 247686.15 | X7: 233812.45 | Y7: 253103.16 | Z7: 295300.03 | AA7: 306365.92 | AB7: 306035.29 | AC7: 353333.5 | AD7: 369672.77 | AE7: 365662.92
A8: Finland | B8: 12897.571 | C8: 15737.055 | D8: 19071.032 | E8: 21214.496 | F8: 23942.111 | G8: 33796.507 | H8: 41872.733 | I8: 63982.111 | J8: 62727.409 | K8: 75699.875 | L8: 93131.536 | M8: 106811.97 | N8: 105982.77 | O8: 120004.72 | P8: 152087.14 | Q8: 167383.32 | R8: 176862.65 | S8: 187187.06 | T8: 173000.64 | U8: 191796.86 | V8: 187892.72 | W8: 154408.02 | X8: 144880.93 | Y8: 153930.22 | Z8: 188974.9 | AA8: 181230.6 | AB8: 198077.89 | AC8: 199882.32 | AD8: 202316.34 | AE8: 202144.17
A9: France | B9: 272808.38 | C9: 300860.46 | D9: 374959.18 | E9: 482738.21 | F9: 598654 | G9: 747300.83 | H9: 351982.93 | I9: 499803.55 | J9: 535081.31 | K9: 590722.21 | L9: 750175.72 | M9: 868343.03 | N9: 911905.8 | O9: 1143186.2 | P9: 1382719.2 | Q9: 1320388.2 | R9: 1504780.8 | S9: 1557047.5 | T9: 1608475.3 | U9: 1708981.9 | V9: 1770993.3 | W9: 1691674.7 | X9: 1632145.3 | Y9: 1641937.9 | Z9: 1843409.3 | AA9: 1854291.7 | AB9: 1880155.3 | AC9: 2035404.6 | AD9: 2034048.7 | AE9: 2044714.9
A10: Germany | B10: 156701.62 | C10: 188318.05 | D10: 234134.64 | E10: 250140.21 | F10: 319659.62 | G10: 391185.3 | H10: 460398.13 | I10: 549681.71 | J10: 626348.72 | K10: 725126.76 | L10: 879866.42 | M10: 982490.9 | N10: 996717.91 | O10: 1235955.8 | P10: 1545285.5 | Q10: 1459591.3 | R10: 1605282.2 | S10: 1634923.5 | T10: 1696190.3 | U10: 1928817.7 | V10: 2103930.1 | W10: 1995930.6 | X10: 1958383 | Y10: 1992210 | Z10: 2390539.5 | AA10: 2470659.2 | AB10: 2617700.6 | AC10: 2999790.7 | AD10: 2986671.9 | AE10: 3031351.9
A11: Greece | B11: 757.06192 | C11: 854.90318 | D11: 1266.2511 | E11: 1788.0058 | F11: 2177.7243 | G11: 2792 | H11: 3809.4432 | I11: 5851.9145 | J11: 7020.4358 | K11: 9508.5629 | L11: 12949.539 | M11: 14582.643 | N11: 14529.185 | O11: 23450.502 | P11: 33522.661 | Q11: 39584.123 | R11: 48899.726 | S11: 49376.599 | T11: 51677.072 | U11: 48865.298 | V11: 40380.048 | W11: 33438.742 | X11: 28732.97 | Y11: 22365.894 | Z11: 24935.846 | AA11: 23581.275 | AB11: 23038.687 | AC11: 19807.848 | AD11: 20774.149 | AE11: 21746.907
A12: Iceland | B12: 63.307173 | C12: 96.173582 | D12: 250.62088 | E12: 345.20855 | F12: 439.51233 | G12: 499.84132 | H12: 631.59201 | I12: 889.12633 | J12: 987.25595 | K12: 1342.3927 | L12: 2042.2454 | M12: 4427.228 | N12: 10648.476 | O12: 14906.294 | P12: 29528.31 | Q12: 13437.983 | R12: 14682.89 | S12: 12819.826 | T12: 12764.534 | U12: 13648.942 | V12: 18648.706 | W12: 16337.715 | X12: 16257.69 | Y12: 14179.587 | Z12: 6529.8698 | AA12: 6418.4991 | AB12: 6637.4814 | AC12: 6808.5921 | AD12: 6720.8928 | AE12: 6245.5858
A13: Ireland | B13: 28810.854 | C13: 31336.761 | D13: 39899.866 | E13: 47237.543 | F13: 56742.442 | G13: 42143.669 | H13: 50878.519 | I13: 72688.283 | J13: 88034.82 | K13: 133081.08 | L13: 192118.72 | M13: 275292.67 | N13: 342409.1 | O13: 401918.11 | P13: 485583.96 | Q13: 522536.03 | R13: 672185.4 | S13: 700103.33 | T13: 709704.15 | U13: 809440.03 | V13: 981810.25 | W13: 1107710.8 | X13: 1443396.3 | Y13: 1490290.8 | Z13: 1635059.7 | AA13: 1693575.2 | AB13: 1680433.4 | AC13: 1804273.8 | AD13: 2085345.4 | AE13: 1812836
... A26: United States | B26: 1204611 | C26: 1234084 | D26: 1493609 | E26: 1749299 | F26: 2036671 | G26: 2469095 | H26: 3051404 | I26: 2934570 | J26: 2554463 | K26: 2283141 | L26: 3037312 | M26: 3746863 | N26: 4047170 | O26: 4929892 | P26: 5857923 | Q26: 3707211 | R26: 4945292 | S26: 5486391 | T26: 5214826 | U26: 5969502 | V26: 7120688 | W26: 7242129 | X26: 7057108 | Y26: 7403191 | Z26: 8893940 | AA26: 7417363 | AB26: 8668834 | AC26: 9349445 | AD26: 10925509 | AE26: 9276999

Sheet Portfolio equity liabilities 
A1: Country | K1: Portfolio equity liabilities
A2: Year | B2: 1993 | C2: 1994 | D2: 1995 | E2: 1996 | F2: 1997 | G2: 1998 | H2: 1999 | I2: 2000 | J2: 2001 | K2: 2002 | L2: 2003 | M2: 2004 | N2: 2005 | O2: 2006 | P2: 2007 | Q2: 2008 | R2: 2009 | S2: 2010 | T2: 2011 | U2: 2012 | V2: 2013 | W2: 2014 | X2: 2015 | Y2: 2016 | Z2: 2017 | AA2: 2018 | AB2: 2019 | AC2: 2020 | AD2: 2021 | AE2: 2022
A3: Australia | B3: 35939.114 | C3: 46570.712 | D3: 51341.675 | E3: 61154.48 | F3: 60327.104 | G3: 73020.337 | H3: 100804.85 | I3: 84947.036 | J3: 89130.336 | K3: 87368.057 | L3: 138978 | M3: 146733.22 | N3: 182379.48 | O3: 252366.14 | P3: 325898.43 | Q3: 173251.27 | R3: 336652.31 | S3: 402395.85 | T3: 341019.18 | U3: 398184.78 | V3: 386835.8 | W3: 373755.3 | X3: 335907.96 | Y3: 381296.68 | Z3: 458655.6 | AA3: 385148 | AB3: 462936.86 | AC3: 528446.54 | AD3: 583314.19 | AE3: 565014.68
A4: Austria | B4: 3590.546 | C4: 5378.7948 | D4: 6988.5012 | E4: 9056.0526 | F4: 15661.68 | G4: 15622.806 | H4: 14745.016 | I4: 19569.345 | J4: 14919.797 | K4: 17235.445 | L4: 26470.54 | M4: 45181.277 | N4: 59235.693 | O4: 92955.177 | P4: 105124.13 | Q4: 46804.263 | R4: 60307.838 | S4: 62709.202 | T4: 47413.672 | U4: 57855.69 | V4: 65576.205 | W4: 54785.048 | X4: 54703.909 | Y4: 56828.639 | Z4: 85998.205 | AA4: 63700.93 | AB4: 73615.279 | AC4: 78889.032 | AD4: 92830.161 | AE4: 67491.248
A5: Belgium | B5: 8252.5616 | C5: 9736.9454 | D5: 10011.899 | E5: 11173.254 | F5: 12099.133 | G5: 17842.63 | H5: 15470.84 | I5: 14236.65 | J5: 15663.345 | K5: 18059.663 | L5: 27884.514 | M5: 44250.543 | N5: 43015.401 | O5: 57745.182 | P5: 72899.864 | Q5: 55814.128 | R5: 107402.49 | S5: 107017.59 | T5: 99243.424 | U5: 141514.89 | V5: 187040.44 | W5: 195273.42 | X5: 215728.08 | Y5: 219182.18 | Z5: 264747.87 | AA5: 190408.92 | AB5: 235456.78 | AC5: 229875.1 | AD5: 241155.46 | AE5: 199455.27
A6: Canada | B6: 41005.843 | C6: 44812.446 | D6: 57054.99 | E6: 79913.583 | F6: 84974.68 | G6: 92862.18 | H6: 145243.82 | I6: 152328.56 | J6: 113270.3 | K6: 99394.957 | L6: 172321.6 | M6: 225899.24 | N6: 280843.39 | O6: 346101.13 | P6: 418081.03 | Q6: 209170.89 | R6: 353642.88 | S6: 462355.38 | T6: 409846.95 | U6: 442094.38 | V6: 432507.14 | W6: 449884.5 | X6: 357797.21 | Y6: 463699.33 | Z6: 586724.59 | AA6: 507835.46 | AB6: 625580.04 | AC6: 638867.23 | AD6: 791566.1 | AE6: 702797.35
A7: Denmark | B7: 3248.4312 | C7: 6740.0953 | D7: 8294.2661 | E7: 12448.482 | F7: 20363.317 | G7: 20556.173 | H7: 20740.255 | I7: 26023.315 | J7: 23842.4 | K7: 20671.503 | L7: 31257.85 | M7: 44458.783 | N7: 49096.63 | O7: 62886.389 | P7: 83226.213 | Q7: 45686.2 | R7: 67033.39 | S7: 92773.591 | T7: 78595.447 | U7: 107299.57 | V7: 146634.58 | W7: 165487.63 | X7: 202786.82 | Y7: 172432.65 | Z7: 236789.63 | AA7: 186779 | AB7: 238411.15 | AC7: 343747.85 | AD7: 412086.81 | AE7: 373504.78
A8: Finland | B8: 5251.1021 | C8: 12767.33 | D8: 14625.338 | E8: 23456.793 | F8: 28870.257 | G8: 79721.743 | H8: 219531.22 | I8: 204361.06 | J8: 128038.79 | K8: 89172.754 | L8: 103315.11 | M8: 102974.34 | N8: 119951.97 | O8: 154812.8 | P8: 229908.31 | Q8: 96964.179 | R8: 104051.7 | S8: 97396.473 | T8: 66877.77 | U8: 83513.455 | V8: 113430.98 | W8: 110717.42 | X8: 112005.46 | Y8: 119495.94 | Z8: 147852.1 | AA8: 160208.4 | AB8: 167796.64 | AC8: 203844.62 | AD8: 247221.66 | AE8: 194283.32
A9: France | B9: 103818.17 | C9: 102207.26 | D9: 120755.1 | E9: 155317.93 | F9: 208580.35 | G9: 300439.34 | H9: 482208 | I9: 502116.41 | J9: 415991.23 | K9: 345112.49 | L9: 490900.31 | M9: 593864.7 | N9: 690443.02 | O9: 990330 | P9: 1060372.8 | Q9: 624815.84 | R9: 825769.74 | S9: 774024.13 | T9: 647730.57 | U9: 810994.28 | V9: 1009175.7 | W9: 902179.5 | X9: 853477.66 | Y9: 867849.17 | Z9: 1096312.4 | AA9: 920743.16 | AB9: 1071666 | AC9: 1113341.7 | AD9: 1325564.8 | AE9: 1117951.6
A10: Germany | B10: 93608.295 | C10: 99506.069 | D10: 110776.42 | E10: 140288.78 | F10: 186976.17 | G10: 289976.09 | H10: 375408.97 | I10: 300752.49 | J10: 294687.33 | K10: 212677.41 | L10: 362453.21 | M10: 399719.14 | N10: 449332.39 | O10: 820184.14 | P10: 1173072.3 | Q10: 525103.72 | R10: 768754.58 | S10: 831259.37 | T10: 728749.06 | U10: 939540.78 | V10: 1249522.5 | W10: 1180321.3 | X10: 1129649.3 | Y10: 1124478 | Z10: 1445552.3 | AA10: 1120312.7 | AB10: 1320899.3 | AC10: 1438562.5 | AD10: 1493735.2 | AE10: 1093135.9
A11: Greece | B11: 1450.9923 | C11: 2111.8727 | D11: 2917.6321 | E11: 4368.4294 | F11: 5625.004 | G11: 12001 | H11: 15210.649 | I11: 9584.15 | J11: 7711.375 | K11: 8425.2558 | L11: 16139.877 | M11: 28386.164 | N11: 37962.746 | O11: 60247.482 | P11: 93547.539 | Q11: 23892.706 | R11: 28114.75 | S11: 17106.032 | T11: 7480.0359 | U11: 10391.594 | V11: 13300.04 | W11: 16945.194 | X11: 16539.53 | Y11: 14755.292 | Z11: 19074.867 | AA11: 13103.38 | AB11: 18916.933 | AC11: 15289.666 | AD11: 21970.175 | AE11: 25219.757
A12: Iceland | B12: 0.46433676 | C12: 0.60383708 | D12: 1.0280769 | E12: 2.4370003 | F12: 1.7292005 | G12: 6.4168631 | H12: 60.372451 | I12: 30.747258 | J12: 117.82419 | K12: 236.41102 | L12: 292.97084 | M12: 781.25819 | N12: 3722.007 | O12: 4992.3109 | P12: 5845.384 | Q12: 103.66562 | R12: 493.85108 | S12: 465.96262 | T12: 465.21881 | U12: 463.98946 | V12: 590.72263 | W12: 599.49567 | X12: 713.96713 | Y12: 802.62365 | Z12: 1223.4821 | AA12: 1397.6962 | AB12: 2652.1883 | AC12: 2936.1371 | AD12: 3035.6496 | AE12: 2069.3185
A13: Ireland | B13: 16319.975 | C13: 20612.313 | D13: 30857.853 | E13: 44596.626 | F13: 63195.043 | G13: 109688.5 | H13: 160645.59 | I13: 217502.51 | J13: 279224.92 | K13: 343771.2 | L13: 481711.99 | M13: 613830.36 | N13: 712329.99 | O13: 950794.98 | P13: 1155092.1 | Q13: 889190.53 | R13: 1177526.3 | S13: 1407712.1 | T13: 1482030.5 | U13: 1771677.1 | V13: 2092944.2 | W13: 2351774.8 | X13: 2518358 | Y13: 2582621.9 | Z13: 3244308 | AA13: 3122831.8 | AB13: 3816112.3 | AC13: 4479826.7 | AD13: 5191368.4 | AE13: 4279407.2
... A26: United States | B26: 373521 | C26: 397720 | D26: 549513 | E26: 672397 | F26: 952893 | G26: 1250342 | H26: 1611534 | I26: 1643205 | J26: 1572681 | K26: 1335792 | L26: 1839509 | M26: 2123259 | N26: 2304013 | O26: 2791893 | P26: 3231651 | Q26: 2132433 | R26: 2917681 | S26: 3545769 | T26: 3841901 | U26: 4545361 | V26: 5864600 | W26: 6642507 | X26: 6209080 | Y26: 6570218 | Z26: 7941551 | AA26: 7539222 | AB26: 9296241 | AC26: 11834628 | AD26: 15250615 | AE26: 12054191

Sheet Portfolio debt liabilities 
A1: Country | K1: Portfolio debt liabilities
A2: Year | B2: 1993 | C2: 1994 | D2: 1995 | E2: 1996 | F2: 1997 | G2: 1998 | H2: 1999 | I2: 2000 | J2: 2001 | K2: 2002 | L2: 2003 | M2: 2004 | N2: 2005 | O2: 2006 | P2: 2007 | Q2: 2008 | R2: 2009 | S2: 2010 | T2: 2011 | U2: 2012 | V2: 2013 | W2: 2014 | X2: 2015 | Y2: 2016 | Z2: 2017 | AA2: 2018 | AB2: 2019 | AC2: 2020 | AD2: 2021 | AE2: 2022
A3: Australia | B3: 147173.48 | C3: 161939.72 | D3: 174379.07 | E3: 204596.58 | F3: 191238.95 | G3: 194006.66 | H3: 222339.6 | I3: 223861.78 | J3: 224252.53 | K3: 270665.59 | L3: 376270.72 | M3: 450550.29 | N3: 501922.43 | O3: 634968.86 | P3: 765498.08 | Q3: 707495.77 | R3: 913179.7 | S3: 1037250 | T3: 1156910.4 | U3: 1261043.5 | V3: 1208994.5 | W3: 1219123.2 | X3: 1223585.4 | Y3: 1214377.4 | Z3: 1346782.5 | AA3: 1308063 | AB3: 1344741.1 | AC3: 1468345.1 | AD3: 1444447.4 | AE3: 1351468.5
A4: Austria | B4: 118857.48 | C4: 137055.98 | D4: 165402.94 | E4: 162097.88 | F4: 163791.96 | G4: 197339.37 | H4: 224503 | I4: 248417.82 | J4: 265346.57 | K4: 319153.43 | L4: 400343.18 | M4: 485674.19 | N4: 500212.47 | O4: 624960.65 | P4: 747422.26 | Q4: 772436.86 | R4: 761452.89 | S4: 729423.81 | T4: 743674.47 | U4: 768445.7 | V4: 768067.53 | W4: 686215.36 | X4: 598311.45 | Y4: 569802.59 | Z4: 629274.9 | AA4: 609832.77 | AB4: 620302.47 | AC4: 700197.91 | AD4: 674458.4 | AE4: 628326.36
A5: Belgium | B5: 335809.14 | C5: 380700.53 | D5: 431282.52 | E5: 407175.97 | F5: 386825.66 | G5: 404457.41 | H5: 419383.29 | I5: 401770.78 | J5: 430202.15 | K5: 541953.55 | L5: 731850.29 | M5: 873387.04 | N5: 913670.45 | O5: 1086741.4 | P5: 1430108.2 | Q5: 1342478.4 | R5: 1232074.2 | S5: 1093340.1 | T5: 1080121.6 | U5: 1046867.5 | V5: 953359.07 | W5: 927021.34 | X5: 841077.24 | Y5: 876181.32 | Z5: 973628.73 | AA5: 906334.38 | AB5: 974160.5 | AC5: 1103761 | AD5: 1077107.5 | AE5: 1023643.8
A6: Canada | B6: 386955.37 | C6: 387114.01 | D6: 430301.62 | E6: 449359.52 | F6: 475019.64 | G6: 487914.94 | H6: 457978.91 | I6: 433413.93 | J6: 457379.65 | K6: 497447.87 | L6: 552387.18 | M6: 577851.08 | N6: 614835 | O6: 670224.15 | P6: 786355.31 | Q6: 768266.55 | R6: 920332.93 | S6: 1050238.6 | T6: 1169459.8 | U6: 1377073.6 | V6: 1359122.7 | W6: 1439510.5 | X6: 1443574.8 | Y6: 1570779.2 | Z6: 1789345.4 | AA6: 1790654 | AB6: 2120097.4 | AC6: 2378070.8 | AD6: 2534475.3 | AE6: 2577028.3
A7: Denmark | B7: 137565.72 | C7: 127172.18 | D7: 139104.68 | E7: 153339.88 | F7: 155090.44 | G7: 181801.68 | H7: 171396.22 | I7: 166439.14 | J7: 169667.15 | K7: 208159.88 | L7: 270088.86 | M7: 317566.74 | N7: 322166.27 | O7: 402691.1 | P7: 514820.71 | Q7: 529902.36 | R7: 548763.76 | S7: 547996.2 | T7: 521511.79 | U7: 532762.47 | V7: 556090.25 | W7: 485771.59 | X7: 422513.42 | Y7: 424282.75 | Z7: 490382.61 | AA7: 436956.78 | AB7: 436950.07 | AC7: 531546.73 | AD7: 492469.89 | AE7: 400077.65
A8: Finland | B8: 77732.34 | C8: 89099.561 | D8: 88012.777 | E8: 85473.384 | F8: 80344.719 | G8: 89920.888 | H8: 84900.702 | I8: 99527.953 | J8: 108350.97 | K8: 129999.37 | L8: 156084.9 | M8: 192416.4 | N8: 182828.62 | O8: 227433.08 | P8: 265105.66 | Q8: 271289.54 | R8: 349006.53 | S8: 391286.85 | T8: 472948.91 | U8: 539098.43 | V8: 531101.46 | W8: 489693.23 | X8: 418808.79 | Y8: 394918.59 | Z8: 422543.98 | AA8: 524487.7 | AB8: 537026.99 | AC8: 581348.63 | AD8: 518267.6 | AE8: 540116.7
A9: France | B9: 752186.34 | C9: 804545.02 | D9: 925156.23 | E9: 887250.72 | F9: 890987.92 | G9: 991271.64 | H9: 993164.71 | I9: 1091528.4 | J9: 1257677.4 | K9: 1578943.4 | L9: 2109505.9 | M9: 2630142.3 | N9: 2818924.4 | O9: 3528559.3 | P9: 4547056.4 | Q9: 4599079.9 | R9: 4946622.3 | S9: 4963036.3 | T9: 4747328.5 | U9: 5010509.8 | V9: 5143339 | W9: 5002149.4 | X9: 4582126.1 | Y9: 4571702.7 | Z9: 5317640.6 | AA9: 5533852.1 | AB9: 5931550.2 | AC9: 7009545.9 | AD9: 6795912.6 | AE9: 6341523.5
A10: Germany | B10: 916600.2 | C10: 1053139.6 | D10: 1324221.1 | E10: 1369863 | F10: 1287510 | G10: 1659584 | H10: 1740810.2 | I10: 1864379.9 | J10: 1932322.1 | K10: 2482504.3 | L10: 3043576.8 | M10: 3534308.2 | N10: 3396501.3 | O10: 3971704.6 | P10: 4827264.3 | Q10: 4839972.2 | R10: 4809463.3 | S10: 4926205.6 | T10: 5030998.5 | U10: 5180482 | V10: 4907931.6 | W10: 4620272.6 | X10: 4179863.6 | Y10: 4205936.5 | Z10: 4744284.4 | AA10: 4650815.8 | AB10: 4677889.3 | AC10: 5583511.2 | AD10: 5737884.8 | AE10: 5243540
A11: Greece | B11: 40960.865 | C11: 44380.865 | D11: 50302.865 | E11: 52411.865 | F11: 60011.865 | G11: 66599.792 | H11: 72210.11 | I11: 84761.092 | J11: 98240.849 | K11: 144981.97 | L11: 204482.13 | M11: 252918.89 | N11: 263937.17 | O11: 331608.16 | P11: 452431.19 | Q11: 504322.29 | R11: 593521.98 | S11: 548942.98 | T11: 495091.91 | U11: 588007.61 | V11: 579501.54 | W11: 505724.72 | X11: 471810.49 | Y11: 445178.05 | Z11: 474556.56 | AA11: 466713.17 | AB11: 493405.03 | AC11: 596584.43 | AD11: 619027.41 | AE11: 575132.5
A12: Iceland | B12: 4026.2576 | C12: 4085.5292 | D12: 4264.7719 | E12: 4431.6684 | F12: 4607.3989 | G12: 5838.3524 | H12: 6767.0839 | I12: 8518.4042 | J12: 9061.8747 | K12: 11083.763 | L12: 16041.611 | M12: 26534.789 | N12: 45348.762 | O12: 70498.688 | P12: 110500.97 | Q12: 112314.5 | R12: 109543.72 | S12: 109272.9 | T12: 99141.31 | U12: 91438.205 | V12: 95556.3 | W12: 85911.511 | X12: 21593.307 | Y12: 15703.623 | Z12: 15994.855 | AA12: 15546.191 | AB12: 14674.438 | AC12: 15356.293 | AD12: 17049.842 | AE12: 16432.83
A13: Ireland | B13: 55185.759 | C13: 61251.294 | D13: 95826.262 | E13: 123152.07 | F13: 151112.16 | G13: 228820.68 | H13: 292234.12 | I13: 296082.31 | J13: 348848.01 | K13: 470206.8 | L13: 695414.11 | M13: 972670.16 | N13: 1152137.2 | O13: 1554107.4 | P13: 1995333.9 | Q13: 2070755.8 | R13: 2048872.9 | S13: 1806078.4 | T13: 1865128.4 | U13: 1829612.1 | V13: 1892522 | W13: 1815826.8 | X13: 1715826.2 | Y13: 1636778.6 | Z13: 1869634.8 | AA13: 1971534.1 | AB13: 2186115.6 | AC13: 2526013.7 | AD13: 2594879.8 | AE13: 2415595.5
... A26: United States | B26: 2071273.8 | C26: 2269873.6 | D26: 2686887.1 | E26: 3077629.3 | F26: 3577050.7 | G26: 3783522.7 | H26: 3992218.7 | I26: 4511576.6 | J26: 5092559.4 | K26: 5857966 | L26: 6311376.6 | M26: 7727686 | N26: 8551594.7 | O26: 10494677 | P26: 12130246 | Q26: 12227230 | R26: 12154330 | S26: 13092822 | T26: 13992593 | U26: 14310394 | V26: 14894342 | W26: 15640128 | X26: 15565024 | Y26: 15917747 | Z26: 17112817 | AA26: 17562291 | AB26: 18990397 | AC26: 20481300 | AD26: 21710927 | AE26: 21013368

Sheet FDI liabilities
A1: Country | K1: Portfolio debt liabilities
A2: Year | B2: 1993 | C2: 1994 | D2: 1995 | E2: 1996 | F2: 1997 | G2: 1998 | H2: 1999 | I2: 2000 | J2: 2001 | K2: 2002 | L2: 2003 | M2: 2004 | N2: 2005 | O2: 2006 | P2: 2007 | Q2: 2008 | R2: 2009 | S2: 2010 | T2: 2011 | U2: 2012 | V2: 2013 | W2: 2014 | X2: 2015 | Y2: 2016 | Z2: 2017 | AA2: 2018 | AB2: 2019 | AC2: 2020 | AD2: 2021 | AE2: 2022
A3: Australia | B3: 87643.147 | C3: 101343.66 | D3: 111310.45 | E3: 122701.64 | F3: 106451.46 | G3: 113102.48 | H3: 127144.49 | I3: 118857.93 | J3: 121924.64 | K3: 150335.16 | L3: 213910.5 | M3: 284951.97 | N3: 271534.3 | O3: 332081.71 | P3: 428108.49 | Q3: 339293.95 | R3: 471276.1 | S3: 561189.68 | T3: 595341.67 | U3: 654463.05 | V3: 602890.92 | W3: 618156.85 | X3: 616171.97 | Y3: 655124.28 | Z3: 748988.76 | AA3: 738079.76 | AB3: 764167.54 | AC3: 827053.85 | AD3: 809025.13 | AE3: 823737.7
A4: Austria | B4: 11397.513 | C4: 13246.422 | D4: 17535.686 | E4: 18258.171 | F4: 19694.451 | G4: 23836.58 | H4: 23991.254 | I4: 31279.502 | J4: 35163.996 | K4: 44618.102 | L4: 56529.736 | M4: 74500.128 | N4: 154666.35 | O4: 216232.96 | P4: 313267.3 | Q4: 297278.25 | R4: 336457.89 | S4: 295848.04 | T4: 292228.61 | U4: 313889.22 | V4: 335957.03 | W4: 314602.45 | X4: 282443.62 | Y4: 244849.51 | Z4: 315152.05 | AA4: 270856.62 | AB4: 259207.7 | AC4: 275124.41 | AD4: 278361.37 | AE4: 272989.87
A5: Belgium | B5: 94295.209 | C5: 105881.43 | D5: 112959.88 | E5: 123882.99 | F5: 128728.11 | G5: 180491.81 | H5: 179923.86 | I5: 195218.9 | J5: 203537.12 | K5: 255745.42 | L5: 357137.25 | M5: 471071.39 | N5: 478183.14 | O5: 618531.68 | P5: 784576.3 | Q5: 952095.37 | R5: 1071934.6 | S5: 1117776.7 | T5: 1178193 | U5: 1243063.5 | V5: 1256721.4 | W5: 1110065 | X5: 1022136.9 | Y5: 1006194.3 | Z5: 1074743.1 | AA5: 987847.6 | AB5: 998040.92 | AC5: 1032116.3 | AD5: 971877.26 | AE5: 907692.6
A6: Canada | B6: 188234.99 | C6: 182531.1 | D6: 209369.58 | E6: 260409.23 | F6: 284888.84 | G6: 272471.8 | H6: 314921.54 | I6: 347231.17 | J6: 337935.72 | K6: 313753.46 | L6: 465153.87 | M6: 574098.99 | N6: 669137.53 | O6: 740477.52 | P6: 1067622.7 | Q6: 663003.42 | R6: 907116.53 | S6: 1037189.1 | T6: 902885.12 | U6: 1004698.9 | V6: 1037531.7 | W6: 1040124.6 | X6: 864233.1 | Y6: 962655.23 | Z6: 1000347.6 | AA6: 994431.07 | AB6: 1301055.6 | AC6: 1281395.4 | AD6: 1539772.5 | AE6: 1553670
A7: Denmark | B7: 18456.995 | C7: 23672.53 | D7: 30111.792 | E7: 26579.191 | F7: 26076.765 | G7: 35663.039 | H7: 47235.227 | I7: 73439.062 | J7: 75437.898 | K7: 82808.732 | L7: 100191.18 | M7: 116541.08 | N7: 116123.72 | O7: 132759.03 | P7: 161517.74 | Q7: 151986.6 | R7: 155210.11 | S7: 140296.08 | T7: 141095.45 | U7: 146044.42 | V7: 148852.88 | W7: 161249.06 | X7: 149047.14 | Y7: 168256.15 | Z7: 190524.35 | AA7: 199851.52 | AB7: 195420.54 | AC7: 229847.3 | AD7: 231294.28 | AE7: 240489.66
A8: Finland | B8: 7936.2088 | C8: 9917.1445 | D8: 12542.33 | E8: 12346.088 | F8: 13174.498 | G8: 20844.192 | H8: 26342.621 | I8: 36145.272 | J8: 34572.518 | K8: 45753.722 | L8: 67338.462 | M8: 79168.616 | N8: 78924.112 | O8: 94365.803 | P8: 127258.45 | Q8: 136778.17 | R8: 131796.07 | S8: 136221.55 | T8: 128451.48 | U8: 137048.73 | V8: 131244.81 | W8: 130713.65 | X8: 131929.75 | Y8: 124921.39 | Z8: 154052.48 | AA8: 124513.02 | AB8: 137428.89 | AC8: 145790.52 | AD8: 147129.27 | AE8: 146048.47
A9: France | B9: 307160.66 | C9: 301833.15 | D9: 341102.04 | E9: 359211.38 | F9: 399726.12 | G9: 548620.62 | H9: 254712.66 | I9: 282423.21 | J9: 309585.09 | K9: 396830.53 | L9: 534435.81 | M9: 653852.73 | N9: 644728.4 | O9: 813434.18 | P9: 996311.34 | Q9: 949171.11 | R9: 1032312.5 | S9: 1014764.2 | T9: 1054978.9 | U9: 1116928.8 | V9: 1206941.4 | W9: 1097518.5 | X9: 1051329.3 | Y9: 1051945.1 | Z9: 1222318 | AA9: 1208102.8 | AB9: 1274242.3 | AC9: 1431398.2 | AD9: 1453018 | AE9: 1451709.4
A10: Germany | B10: 71169.553 | C10: 85717.33 | D10: 101477.5 | E10: 101732.7 | F10: 214115.28 | G10: 278374.78 | H10: 337975.57 | I10: 525520.35 | J10: 492102.06 | K10: 651675.81 | L10: 825529.64 | M10: 887081.25 | N10: 813160.13 | O10: 1029899.3 | P10: 1246940.8 | Q10: 1137226.3 | R10: 1212374.4 | S10: 1210518.4 | T10: 1252020.3 | U10: 1447955.7 | V10: 1599365.7 | W10: 1469339 | X10: 1391420.7 | Y10: 1417595.8 | Z10: 1715996.8 | AA10: 1755565.5 | AB10: 1808553.8 | AC10: 2161688.8 | AD10: 2088445.3 | AE10: 2019117.5
A11: Greece | B11: 9339.7975 | C11: 11179.225 | D11: 12694.081 | E11: 13434.037 | F11: 12809.578 | G11: 13084 | H11: 15386.454 | I11: 12479.866 | J11: 13941.285 | K11: 16068.181 | L11: 23066.169 | M11: 29272.891 | N11: 30116.561 | O11: 42320.478 | P11: 55093.342 | Q11: 40470.636 | R11: 47381.334 | S11: 41778.965 | T11: 32691.677 | U11: 29111.242 | V11: 29949.915 | W11: 25573.802 | X11: 28395.473 | Y11: 28975.101 | Z11: 38234.883 | AA11: 39820.81 | AB11: 48956.649 | AC11: 45212.499 | AD11: 49380.227 | AE11: 55627.456
A12: Iceland | B12: 66.253614 | C12: 73.654889 | D12: 170.19776 | E12: 135.9396 | F12: 230.02217 | G12: 384.21812 | H12: 522.56375 | I12: 511.88902 | J12: 830.69451 | K12: 882.9238 | L12: 1502.0848 | M12: 2475.3932 | N12: 5265.7034 | O12: 8610.494 | P12: 20824.85 | Q12: 13239.907 | R12: 13124.404 | S12: 13137.514 | T12: 13899.552 | U12: 11711.055 | V12: 16538.018 | W12: 15844.791 | X12: 16472.181 | Y12: 17962.303 | Z12: 11391.592 | AA12: 9937.6085 | AB12: 9745.8299 | AC12: 9096.9263 | AD12: 9762.5786 | AE12: 10498.923
A13: Ireland | B13: 33851.26 | C13: 35646.033 | D13: 43236.591 | E13: 50708.817 | F13: 60088.94 | G13: 84115.166 | H13: 98462.402 | I13: 171851.67 | J13: 181267.55 | K13: 257098.24 | L13: 341635.18 | M13: 376248.8 | N13: 401786.94 | O13: 437681.24 | P13: 539206.68 | Q13: 546858.77 | R13: 642821.65 | S13: 628190.38 | T13: 669386.23 | U13: 780591.34 | V13: 861791.32 | W13: 918722.83 | X13: 1423854.1 | Y13: 1474353.9 | Z13: 1706223.7 | AA13: 1774313.8 | AB13: 1746880.3 | AC13: 1952862.2 | AD13: 2018783.6 | AE13: 1980844.7
... A26: United States | B26: 911710 | C26: 877354 | D26: 1135542 | E26: 1370076 | F26: 1794795 | G26: 2368530 | H26: 3009958 | I26: 3023792 | J26: 2799823 | K26: 2282370 | L26: 2763061 | M26: 3101450 | N26: 3227144 | O26: 3752602 | P26: 4134239 | Q26: 3091240 | R26: 3618630 | S26: 4099097 | T26: 4199225 | U26: 4662434 | V26: 5814935 | W26: 6378893 | X26: 6729220 | Y26: 7510517 | Z26: 8835252 | AA26: 8393517 | AB26: 10454728 | AC26: 11875581 | AD26: 14882645 | AE26: 12262731

Sheet GDP
A1: Country | K1: GDP
A2: Year | B2: 1993 | C2: 1994 | D2: 1995 | E2: 1996 | F2: 1997 | G2: 1998 | H2: 1999 | I2: 2000 | J2: 2001 | K2: 2002 | L2: 2003 | M2: 2004 | N2: 2005 | O2: 2006 | P2: 2007 | Q2: 2008 | R2: 2009 | S2: 2010 | T2: 2011 | U2: 2012 | V2: 2013 | W2: 2014 | X2: 2015 | Y2: 2016 | Z2: 2017 | AA2: 2018 | AB2: 2019 | AC2: 2020 | AD2: 2021 | AE2: 2022
A3: Australia | B3: 309307 | C3: 353372 | D3: 379069 | E3: 424687 | F3: 426422 | G3: 381385 | H3: 411725 | I3: 399959 | J3: 377778 | K3: 425285 | L3: 541060 | M3: 658568 | N3: 735936 | O3: 782794 | P3: 949528 | Q3: 1056477 | R3: 1000798 | S3: 1254473 | T3: 1515073 | U3: 1569414 | V3: 1519034 | W3: 1456624 | X3: 1233105 | Y3: 1263521 | Z3: 1381656 | AA3: 1417059 | AB3: 1385482 | AC3: 1360849 | AD3: 1645304 | AE3: 1702554
A4: Austria | B4: 190383.34 | C4: 203970.22 | D4: 241234.44 | E4: 237342.6 | F4: 213045.24 | G4: 218556.72 | H4: 217474.88 | I4: 197376.9 | J4: 197510.14 | K4: 214243.35 | L4: 262208 | M4: 301320.65 | N4: 316267.08 | O4: 336297.82 | P4: 389231.49 | Q4: 432004.59 | R4: 401322.61 | S4: 392595.44 | T4: 431609 | U4: 409661 | V4: 430197 | W4: 442699 | X4: 382010 | Y4: 395728 | Z4: 417114 | AA4: 455198 | AB4: 444670 | AC4: 434877 | AD4: 480688 | AE4: 471026
A5: Belgium | B5: 218720.38 | C5: 238622.03 | D5: 288300.62 | E5: 279291.71 | F5: 253022.5 | G5: 258875.58 | H5: 258500.43 | I5: 236896.7 | J5: 236747.85 | K5: 258200.17 | L5: 318003.79 | M5: 369047.5 | N5: 385927.21 | O5: 408280.84 | P5: 470977.8 | Q5: 517269.79 | R5: 482729.72 | S5: 481813.94 | T5: 523238.54 | U5: 496467.45 | V5: 521799 | W5: 535529 | X5: 462383 | Y5: 475931 | Z5: 502587 | AA5: 543546 | AB5: 535924 | AC5: 524792 | AD5: 594748 | AE5: 579059
A6: Canada | B6: 579059 | C6: 579913.16 | D6: 605941.04 | E6: 630597.99 | F6: 655010.32 | G6: 634003.8 | H6: 678416.73 | I6: 744631.34 | J6: 738967.89 | K6: 760148.66 | L6: 895598.84 | M6: 1026473.4 | N6: 1173505 | O6: 1319355.5 | P6: 1468895.7 | Q6: 1552864.1 | R6: 1376509.2 | S6: 1617345.3 | T6: 1793326.6 | U6: 1828362.5 | V6: 1846595.5 | W6: 1805750.8 | X6: 1556508 | Y6: 1527996 | Z6: 1649266 | AA6: 1725300 | AB6: 1743725 | AC6: 1647598 | AD6: 2001487 | AE6: 2137939
A7: Denmark | B7: 143195 | C7: 156164 | D7: 185008 | E7: 187633 | F7: 173539 | G7: 176991 | H7: 177964 | I7: 164158 | J7: 164791 | K7: 178635 | L7: 218097 | M7: 251375 | N7: 264467 | O7: 282886 | P7: 319424 | Q7: 353359 | R7: 321243 | S7: 321995 | T7: 344003 | U7: 327149 | V7: 343584 | W7: 352994 | X7: 302673 | Y7: 313116 | Z7: 332121 | AA7: 356841 | AB7: 346499 | AC7: 354763 | AD7: 405688 | AE7: 401125
A8: Finland | B8: 89279 | C8: 103738.63 | D8: 134339.49 | E8: 132183.12 | F8: 127076.13 | G8: 134212.32 | H8: 135398.38 | I8: 126075.22 | J8: 129533.99 | K8: 140305.25 | L8: 171609.48 | M8: 197389.81 | N8: 204998.74 | O8: 217100.77 | P8: 256408.29 | Q8: 285685.01 | R8: 253222.27 | S8: 249628.02 | T8: 275555.86 | U8: 258454 | V8: 271366 | W8: 274934 | X8: 234558 | Y8: 240705 | Z8: 255558 | AA8: 275833 | AB8: 268545 | AC8: 271668 | AD8: 296970 | AE8: 283124
A9: France | B9: 1324236 | C9: 1396652.8 | D9: 1602130.1 | E9: 1606034.7 | F9: 1454554.8 | G9: 1505184.2 | H9: 1494634.2 | I9: 1366243 | J9: 1377666.7 | K9: 1500348.5 | L9: 1844082.9 | M9: 2118671.1 | N9: 2198159.6 | O9: 2320659.2 | P9: 2660904.9 | Q9: 2929982.7 | R9: 2697954.7 | S9: 2647348.3 | T9: 2864653.4 | U9: 2685371.1 | V9: 2811917.9 | W9: 2856701 | X9: 2439436 | Y9: 2472282 | Z9: 2594235 | AA9: 2792223 | AB9: 2729171 | AC9: 2645300 | AD9: 2958431 | AE9: 2780136
A10: Germany | B10: 2072457.2 | C10: 2209934.4 | D10: 2588001.9 | E10: 2498113.1 | F10: 2214694.4 | G10: 2242065.2 | H10: 2197124.5 | I10: 1948842.6 | J10: 1945804.2 | K10: 2077015.8 | L10: 2501014 | M10: 2813076.4 | N10: 2848437.8 | O10: 2994862 | P10: 3425982 | Q10: 3744854 | R10: 3407557 | S10: 3402444 | T10: 3748655 | U10: 3529377 | V10: 3733859 | W10: 3890095 | X10: 3357926 | Y10: 3468896 | Z10: 3689547 | AA10: 3976246 | AB10: 3889607 | AC10: 3884615 | AD10: 4281348 | AE10: 4085681
A11: Greece | B11: 109022 | C11: 116678 | D11: 136942 | E11: 145872 | F11: 143326 | G11: 144644 | H11: 149412 | I11: 132198 | J11: 136310 | K11: 154455 | L11: 202320 | M11: 240854 | N11: 248012 | O11: 273562 | P11: 318941 | Q11: 355869 | R11: 330949 | S11: 297368 | T11: 282946 | U11: 242183 | V11: 238911 | W11: 235519 | X11: 195703 | Y11: 193095 | Z11: 199773 | AA11: 212146 | AB11: 205279 | AC11: 188775 | AD11: 215017 | AE11: 219238
A12: Iceland | B12: 6225 | C12: 6393 | D12: 7124 | E12: 7426 | F12: 7570 | G12: 8504 | H12: 8982 | I12: 9026 | J12: 8235 | K12: 9318 | L12: 11429 | M12: 13825 | N12: 16853 | O12: 17465 | P12: 21653 | Q12: 18075 | R12: 13154 | S12: 13751 | T12: 15222 | U12: 14752 | V12: 16125 | W12: 17868 | X12: 17517 | Y12: 20793 | Z12: 24728 | AA12: 26261 | AB12: 24681 | AC12: 21566 | AD12: 25596 | AE12: 28065
A13: Ireland | B13: 51364 | C13: 55843 | D13: 69260 | E13: 75928 | F13: 82957 | G13: 90305 | H13: 98993 | I13: 100253 | J13: 109347 | K13: 128505 | L13: 164630 | M13: 194283 | N13: 211993 | O13: 232193 | P13: 270112 | Q13: 275417 | R13: 236187 | S13: 222096 | T13: 239129 | U13: 225262 | V13: 238115 | W13: 259750 | X13: 292394 | Y13: 298477 | Z13: 337124 | AA13: 386868 | AB13: 398977 | AC13: 428266 | AD13: 513733 | AE13: 533559
... A26: United States | B26: 6858550 | C26: 7287250 | D26: 7639750 | E26: 8073125 | F26: 8577550 | G26: 9062825 | H26: 9631175 | I26: 10250950 | J26: 10581925 | K26: 10929100 | L26: 11456450 | M26: 12217175 | N26: 13039200 | O26: 13815600 | P26: 14474250 | Q26: 14769850 | R26: 14478050 | S26: 15048975 | T26: 15599725 | U26: 16253950 | V26: 16843225 | W26: 17550675 | X26: 18206025 | Y26: 18695100 | Z26: 19477350 | AA26: 20533075 | AB26: 21380950 | AC26: 21060450 | AD26: 23315075 | AE26: 25462725
